[{"image_id": 1005, "score": 0.0516388863325119, "category_id": 7, "segmentation": {"size": [375, 500], "counts": "\\Sg5"}}, {"image_id": 1005, "score": 0.05109706521034241, "category_id": 5, "segmentation": {"size": [375, 500], "counts": "\\Sg5"}}, {"image_id": 1005, "score": 0.050705913454294205, "category_id": 18, "segmentation": {"size": [375, 500], "counts": "\\Sg5"}}, {"image_id": 1005, "score": 0.050326284021139145, "category_id": 13, "segmentation": {"size": [375, 500], "counts": "\\Sg5"}}, {"image_id": 1005, "score": 0.05028878524899483, "category_id": 15, "segmentation": {"size": [375, 500], "counts": "\\Sg5"}}, {"image_id": 1214, "score": 0.0516388863325119, "category_id": 7, "segmentation": {"size": [375, 500], "counts": "jif5;1H000304\\8"}}, {"image_id": 1214, "score": 0.0516388863325119, "category_id": 7, "segmentation": {"size": [375, 500], "counts": "\\Sg5"}}, {"image_id": 1214, "score": 0.05109706521034241, "category_id": 5, "segmentation": {"size": [375, 500], "counts": "\\Sg5"}}, {"image_id": 1214, "score": 0.05109706521034241, "category_id": 5, "segmentation": {"size": [375, 500], "counts": "hif512X1V8"}}, {"image_id": 1214, "score": 0.050705913454294205, "category_id": 18, "segmentation": {"size": [375, 500], "counts": "\\Sg5"}}, {"image_id": 1214, "score": 0.050705913454294205, "category_id": 18, "segmentation": {"size": [375, 500], "counts": "fif526OL10O100070I000X8"}}, {"image_id": 1214, "score": 0.050326284021139145, "category_id": 13, "segmentation": {"size": [375, 500], "counts": "aif5c1X8"}}, {"image_id": 1214, "score": 0.050326284021139145, "category_id": 13, "segmentation": {"size": [375, 500], "counts": "\\Sg5"}}, {"image_id": 1214, "score": 0.05028878524899483, "category_id": 15, "segmentation": {"size": [375, 500], "counts": "aif5c1X8"}}, {"image_id": 1214, "score": 0.05028878524899483, "category_id": 15, "segmentation": {"size": [375, 500], "counts": "\\Sg5"}}, {"image_id": 395, "score": 0.0516388863325119, "category_id": 7, "segmentation": {"size": [333, 500], "counts": "TcR5"}}, {"image_id": 395, "score": 0.0516388863325119, "category_id": 7, "segmentation": {"size": [333, 500], "counts": "TcR5"}}, {"image_id": 395, "score": 0.0516388863325119, "category_id": 7, "segmentation": {"size": [333, 500], "counts": "TcR5"}}, {"image_id": 395, "score": 0.0516388863325119, "category_id": 7, "segmentation": {"size": [333, 500], "counts": "TcR5"}}, {"image_id": 395, "score": 0.0516388863325119, "category_id": 7, "segmentation": {"size": [333, 500], "counts": "_^R51d4"}}, {"image_id": 395, "score": 0.0516388863325119, "category_id": 7, "segmentation": {"size": [333, 500], "counts": "TcR5"}}, {"image_id": 395, "score": 0.0516388863325119, "category_id": 7, "segmentation": {"size": [333, 500], "counts": "TcR5"}}, {"image_id": 395, "score": 0.05109706521034241, "category_id": 5, "segmentation": {"size": [333, 500], "counts": "TcR5"}}, {"image_id": 395, "score": 0.05109706521034241, "category_id": 5, "segmentation": {"size": [333, 500], "counts": "TcR5"}}, {"image_id": 395, "score": 0.05109706521034241, "category_id": 5, "segmentation": {"size": [333, 500], "counts": "TcR5"}}, {"image_id": 395, "score": 0.05109706521034241, "category_id": 5, "segmentation": {"size": [333, 500], "counts": "TcR5"}}, {"image_id": 395, "score": 0.05109706521034241, "category_id": 5, "segmentation": {"size": [333, 500], "counts": "^^R52d4"}}, {"image_id": 395, "score": 0.05109706521034241, "category_id": 5, "segmentation": {"size": [333, 500], "counts": "V^R51m4"}}, {"image_id": 395, "score": 0.05109706521034241, "category_id": 5, "segmentation": {"size": [333, 500], "counts": "TcR5"}}, {"image_id": 395, "score": 0.050705913454294205, "category_id": 18, "segmentation": {"size": [333, 500], "counts": "TcR5"}}, {"image_id": 395, "score": 0.050705913454294205, "category_id": 18, "segmentation": {"size": [333, 500], "counts": "TcR5"}}, {"image_id": 395, "score": 0.050705913454294205, "category_id": 18, "segmentation": {"size": [333, 500], "counts": "_^R51d4"}}, {"image_id": 395, "score": 0.050705913454294205, "category_id": 18, "segmentation": {"size": [333, 500], "counts": "TcR5"}}, {"image_id": 395, "score": 0.050705913454294205, "category_id": 18, "segmentation": {"size": [333, 500], "counts": "TcR5"}}, {"image_id": 395, "score": 0.050705913454294205, "category_id": 18, "segmentation": {"size": [333, 500], "counts": "TcR5"}}, {"image_id": 395, "score": 0.050705913454294205, "category_id": 18, "segmentation": {"size": [333, 500], "counts": "TcR5"}}, {"image_id": 395, "score": 0.050326284021139145, "category_id": 13, "segmentation": {"size": [333, 500], "counts": "TcR5"}}, {"image_id": 395, "score": 0.050326284021139145, "category_id": 13, "segmentation": {"size": [333, 500], "counts": "TcR5"}}, {"image_id": 395, "score": 0.050326284021139145, "category_id": 13, "segmentation": {"size": [333, 500], "counts": "P^R57m4"}}, {"image_id": 395, "score": 0.050326284021139145, "category_id": 13, "segmentation": {"size": [333, 500], "counts": "TcR5"}}, {"image_id": 395, "score": 0.050326284021139145, "category_id": 13, "segmentation": {"size": [333, 500], "counts": "TcR5"}}, {"image_id": 395, "score": 0.050326284021139145, "category_id": 13, "segmentation": {"size": [333, 500], "counts": "TcR5"}}, {"image_id": 395, "score": 0.050326284021139145, "category_id": 13, "segmentation": {"size": [333, 500], "counts": "Y^R58c4"}}, {"image_id": 395, "score": 0.05028878524899483, "category_id": 15, "segmentation": {"size": [333, 500], "counts": "Z^R56d4"}}, {"image_id": 395, "score": 0.05028878524899483, "category_id": 15, "segmentation": {"size": [333, 500], "counts": "TcR5"}}, {"image_id": 395, "score": 0.05028878524899483, "category_id": 15, "segmentation": {"size": [333, 500], "counts": "Q^R56m4"}}, {"image_id": 395, "score": 0.05028878524899483, "category_id": 15, "segmentation": {"size": [333, 500], "counts": "TcR5"}}, {"image_id": 395, "score": 0.05028878524899483, "category_id": 15, "segmentation": {"size": [333, 500], "counts": "TcR5"}}, {"image_id": 395, "score": 0.05028878524899483, "category_id": 15, "segmentation": {"size": [333, 500], "counts": "TcR5"}}, {"image_id": 395, "score": 0.05028878524899483, "category_id": 15, "segmentation": {"size": [333, 500], "counts": "TcR5"}}, {"image_id": 125, "score": 0.9782544374465942, "category_id": 4, "segmentation": {"size": [375, 500], "counts": "g<4=O30_9O]F:FO:O]9L^Fg02C5Af89nFf04GLCo8T1SGGl8:RGIk8c1O1\\GXMW8i2fGYMZ8g2eGZM[8f2fGYMZ8g2fGYMZ8g2hGVMY8j2:010O01O001O010O1O1O00001O01O001N2O001O1O1O1O1N2O001N101O001N11O1O1O001O00001O0O1000001O00000000000000000001N1000000000000O100000000000000000000O1000000000000000000000001O000O10000O100O1O100O100O100O10000O100O1O1O100O100O10000O1000000O010000000000000O100000000000000O10000000000000000000000000000000000000000000001O0000000000000000000000000000001O0000000000000000000000001O0000000000001O00002N1O2N1O1O001O001O00001O000000001O00000000001O00000000000000001O0000001O000010O01O001O1O001O1O10O01OO100O1O00100O100O100O1000000O100000000010O00000010O01O00010O1O010O10O00O1000O10O0100O10000O010000000O1000000001O0010O01O1O100O1O100O010O0010O00000000O101O0000000000000000000O1001O00001O0000001O0000001O000000001O000001O0000000001O000001O00000001O000000000000000001O00000000001O001O1O1O10M201N101O0O10001O0000001O000O10001O00010O00001O1O001O1O1O1O100O001O00001O0O10000O10000O100O100O101O0O100O2O1O001O1N2O1O1O1O1O2gLlGk2e8K2N2N1iMmFh1T9UNoFj1R9TNPGj1R9SNPGm1Q9RNoFn1Q9QNPGo1\\900O10000O1O2N1O1N2O2N1O3N4K2O1N2N3@iE[OY:=Yh1"}}, {"image_id": 125, "score": 0.8965116143226624, "category_id": 4, "segmentation": {"size": [375, 500], "counts": "_<j2b8\\M`Gk2[8;M1000O100O10003N001O1O1O0O00O0M3M3000001100O2O1O000O00O000N201O0101O1O7J0O1000OO00100O10O010000001N1000000O1O1O001M3001O2N1O001O0000O1O1O1N2O1O11O2N1O1O1O0000O1O1O1O1O1O11O1O2N00100OO100O1N2O1O011O01O1O1O1O10O0O0O2O1O1O1001O001O001O1O00O1O1O1O1000O10001O00001N10O1000000O1001O1O1N2O1O1N10O100O2N1O1001N2N2N2N2N2O0O1000000000002BVGiMn8m1e0\\Oe0UOeEGk:Nd_1JmUNNh:4VENh:4VENi:2WEOb_e3"}}, {"image_id": 969, "score": 0.0516388863325119, "category_id": 7, "segmentation": {"size": [377, 500], "counts": "dRh5"}}, {"image_id": 969, "score": 0.05109706521034241, "category_id": 5, "segmentation": {"size": [377, 500], "counts": "dRh5"}}, {"image_id": 969, "score": 0.050705913454294205, "category_id": 18, "segmentation": {"size": [377, 500], "counts": "dRh5"}}, {"image_id": 969, "score": 0.050326284021139145, "category_id": 13, "segmentation": {"size": [377, 500], "counts": "dRh5"}}, {"image_id": 969, "score": 0.05028878524899483, "category_id": 15, "segmentation": {"size": [377, 500], "counts": "dRh5"}}, {"image_id": 950, "score": 0.6978245377540588, "category_id": 7, "segmentation": {"size": [333, 500], "counts": "Q<16[2KjM_7h2fHTMn6Q3nHQMn6Z3N100O1O2O000O100O100O100O1000000O1000000000000000000000000000000000000000000001O000000O100000000000000000000IZLgIf3Y6ZLgIf3Y6ZLgIf3Y6ZLgIf3Y6ZLgIf3Y6ZLgIf3Y6ZLgIf3Y6ZLgIf3Y6ZLgIf3Y6ZLgIf3Y6ZLgIf3Y6ZLgIf3_610000000000000000O1000000000000000000000000000000000000000000000000O1000000O100O100O10O010000001O1O1O001O1O001O00000000001O00000000O1000000O100N2N2O10000O10000000000000000000O2O0000001O0O2O1O001O0O1000O10000O100O100O10000000000O1000000000O2O000000001O001O1O001O000O2O000001O0O10000O10001O0O10000O2O000O2O0001O00001O00001O0O2O00001O0000001O0000O10001O0O10000O10001N10000O10000000000001O000000001O0000001O00000000000000O100O100O100O1000000O10000000000000000000000001O0000000000001O000000000000000000O1000000000000000000000000001O0000001O000000001O0000000000000000000O2O00000000001O00001O00000000000000000000000000000000000000O1001O00000O100O1CXIUMh6j2[ISMf6m2\\IQMe6m2]IRMc6n2^IQMb6n2_IQMb6o2_IPMa6o2`IQM`6o2`IQM`6n2bIQM^6o2bIQM^6n2cIQM^6o2bIQM^6n2`010O1N2O0100O010000O010000000O1000000O1O1M3O1000O10O100000000O10O100000001O0000000000001O000000001O000000O10001N10000O2O0O2O1O0O2O001N100O11O0001O01O00000000010O01O1O0000001O000O2mMmGP1OCT8\\OnG3Nc04HU8@kG4Mb05F_8F_G=;GY8I_G1bb0"}}, {"image_id": 950, "score": 0.1406070739030838, "category_id": 4, "segmentation": {"size": [333, 500], "counts": "j01`04K6HW14dNf6h3XIYL^5JjJ]4S5gKiJ[4U5gKiJ[4V5gKgJ[4W5gKgJZ4Y5gKfJY4[5<001O010OnJQKg4n4XKSKi4l4VKUKk4j4TKWKl4i4SKYKl4g4SKZKn4f4PK[KP5e4PK[KP5e4oJ\\KQ5e4nJ[KR5e4mJ\\KS5d4mJ\\KS5o40000001O00001O0000000O1000000ZLjJPO2a2V5]NjJPO3a2S5^NlJoN31IR2Y5nNlJnN20LS2V5nNmJnN3OKU2U5nNmJnN30JT2U5oNnJmN31HU2V5nNnJmN2c2P5`NnJmN2d2o4_NoJmN2d2o4_NoJmN1e2P5^NoJnN0e2P5]NPKoNMf2S5\\NoJT2Q5lMoJU2P5kMPKU2P5lMoJT2Q5kMPKU2P5kMPKU2P5kMPKU2o4kMRKoNKg2S5ZNRKmNOf2P5]NQKmNOf2P5]NQKlN1f2n4]NRKmN0f2n4]NRKmN0f2n4]NRKmN0f2n4nMlJ_O6M03JT2T5]NlJ_O6L22JT2S5_NkJ_O6L22JT2R5`NlJ^O6M03JT2S5mNSKlN0f2m4^NSKlN0f2m4_NRKkN1f2l4`NSKkNOf2n4_NSKlNMf2o4`NSKP2m4PNSKQ2k4QNSKP2l4QNRKQ2m4XNTKbNO[2m4ROUKcNN[2m4c2O100000000O2O00000O1000000000O1000000000000O100001O000O1000001N10000O100001O00001O000O101O00000000000000O101O0000000O100001O0000001O0000000O2O00000001O000000000000000000000000000001N10000000000O1001O0001O000001O000000000001O00000O101O001O001N100001O0O1000000000000000000001O001O001O1O1O1O1O1O00O001O1O100O100O10000O1001O0O101N101N1O2O0O2N2O0O1000O1000000O1000000O100001O001O001N2O001O00001N100000O1000000000000O100001O001O001N2O001O1O1O1N2O10O001O0010O0001O000001O00001O1N101N2N2N4L7J1N2O1OO10000000000O10000O001002N5J6J7I`0_Oa1aMTZb1"}}, {"image_id": 950, "score": 0.13422076404094696, "category_id": 7, "segmentation": {"size": [333, 500], "counts": "_;3<4OOOe0L[OX7P3fHoLh6`3J5L7I6J3N1N2N2O1N2O1N3N2M4M2N0O2O0001O001O001O1oL`JT1_5ZNbJUO1`2_5YNaJUO21LQ2c5fNaJVO21LR2c5dN`JYO10MS2d5bN_JYO20MT2c5SNYJM5L3NNU2`5dN_JYO2ONU2_5eNaJWO2ONU2]5gNcJUO20MU2Y5jNhJQO20MV2X5iNiJQO20MV2W5jNjJPO20MW2U5jNlJoN20MX2S5jNnJnN20MY2R5iNnJPO2OLZ2R5hNPKoN10M[2P5gNQKnN20M\\2n4gNSKmN20M]2m4fNTKmN20M]2m4fNTKmN21L\\2o4eNSKnN21K\\2Q5eNRKnN22J[2S5dNPKQO1i2P5VNoJQO1i2Q5VNmJQO2i2Q5VNmJQO2h2S5VNkJRO2h2S5VNjJSO2h2U5TNiJUO1f2W5VNgJTO2f2X5UNfJUO2f2X5UNfJUO2f2X5UNfJUO2f2W5UNhJUO1f2V5VNiJTO1f2V5VNjJRO1h2U5VNjJRO1i2S5UNmJRO1h2R5VNmJRO11LX2U5fNoJPO01MZ2S5eNPKoN12MZ2Q5eNQKoN12MZ2P5fNRKnN11N]2m4cNUKoN01N^2l4TNQK_O5N01N`2j4aNWKoN01N\\2n4dNSKPO01NZ2Q5fNPKPO01NX2S5gNnJQO0g2T5YNkJW2V5`1000O1000000O1000O101O000O10000O101O0O10000001N100000000O2O0000000000O2O0O2O1N2O1O1N2O1O1N1010N100O2N1O2M2N3N101N101O0O02O000O2O001N109G1N10001O0001N101O001O0FZKmJg4R5\\KjJe4U5;O000O1000000000O1RKlJc4U5\\KlJc4T5]KlJc4T5\\KmJd4S5\\KmJc4T5]KlJc4T5\\KmJd4S5\\KmJd4S5]KlJc4T5^KjJd4T5;0001N10001N10001N10000000O1000001N100000000000000001O000O2O00001O1N101O00O100O100O10000O10000O100001O0O101O0O1O2N2O0O2N2O1N10O000010O0010O10O0100000O1000001O001O1O002N1O1O1O1OO100O2N1O1O1O1O100O101N1000010O01O01000O3N1N2O000O01O0O100N2O1N2O1N2O1O100O10000100000101N2M100O0010O01O0001O00001O1O2N001O001O00000001O00001O001O0O2O1O1O1O1O00001O00001O001O01O01O001M3CUJTLo5i3=L4bLZIX104Y7bNnHMf0U1f[\\1"}}, {"image_id": 804, "score": 0.0516388863325119, "category_id": 7, "segmentation": {"size": [375, 500], "counts": "ePg56a2"}}, {"image_id": 804, "score": 0.0516388863325119, "category_id": 7, "segmentation": {"size": [375, 500], "counts": "\\Sg5"}}, {"image_id": 804, "score": 0.0516388863325119, "category_id": 7, "segmentation": {"size": [375, 500], "counts": "mPg56Y2"}}, {"image_id": 804, "score": 0.0516388863325119, "category_id": 7, "segmentation": {"size": [375, 500], "counts": "\\Sg5"}}, {"image_id": 804, "score": 0.0516388863325119, "category_id": 7, "segmentation": {"size": [375, 500], "counts": "hPg56^2"}}, {"image_id": 804, "score": 0.0516388863325119, "category_id": 7, "segmentation": {"size": [375, 500], "counts": "UQg55R2"}}, {"image_id": 804, "score": 0.05109706521034241, "category_id": 5, "segmentation": {"size": [375, 500], "counts": "cPg5122a2"}}, {"image_id": 804, "score": 0.05109706521034241, "category_id": 5, "segmentation": {"size": [375, 500], "counts": "\\Sg5"}}, {"image_id": 804, "score": 0.05109706521034241, "category_id": 5, "segmentation": {"size": [375, 500], "counts": "YQg51R2"}}, {"image_id": 804, "score": 0.05109706521034241, "category_id": 5, "segmentation": {"size": [375, 500], "counts": "mPg5140U2"}}, {"image_id": 804, "score": 0.05109706521034241, "category_id": 5, "segmentation": {"size": [375, 500], "counts": "\\Sg5"}}, {"image_id": 804, "score": 0.05109706521034241, "category_id": 5, "segmentation": {"size": [375, 500], "counts": "hPg5122\\2"}}, {"image_id": 804, "score": 0.050705913454294205, "category_id": 18, "segmentation": {"size": [375, 500], "counts": "mPg5120O0X2"}}, {"image_id": 804, "score": 0.050705913454294205, "category_id": 18, "segmentation": {"size": [375, 500], "counts": "\\Sg5"}}, {"image_id": 804, "score": 0.050705913454294205, "category_id": 18, "segmentation": {"size": [375, 500], "counts": "\\Sg5"}}, {"image_id": 804, "score": 0.050705913454294205, "category_id": 18, "segmentation": {"size": [375, 500], "counts": "XQg52R2"}}, {"image_id": 804, "score": 0.050705913454294205, "category_id": 18, "segmentation": {"size": [375, 500], "counts": "mPg51^2"}}, {"image_id": 804, "score": 0.050705913454294205, "category_id": 18, "segmentation": {"size": [375, 500], "counts": "jPg51a2"}}, {"image_id": 804, "score": 0.050326284021139145, "category_id": 13, "segmentation": {"size": [375, 500], "counts": "cPg59`2"}}, {"image_id": 804, "score": 0.050326284021139145, "category_id": 13, "segmentation": {"size": [375, 500], "counts": "\\Sg5"}}, {"image_id": 804, "score": 0.050326284021139145, "category_id": 13, "segmentation": {"size": [375, 500], "counts": "fPg59]2"}}, {"image_id": 804, "score": 0.050326284021139145, "category_id": 13, "segmentation": {"size": [375, 500], "counts": "SQg58Q2"}}, {"image_id": 804, "score": 0.050326284021139145, "category_id": 13, "segmentation": {"size": [375, 500], "counts": "kPg59X2"}}, {"image_id": 804, "score": 0.050326284021139145, "category_id": 13, "segmentation": {"size": [375, 500], "counts": "\\Sg5"}}, {"image_id": 804, "score": 0.05028878524899483, "category_id": 15, "segmentation": {"size": [375, 500], "counts": "\\Sg5"}}, {"image_id": 804, "score": 0.05028878524899483, "category_id": 15, "segmentation": {"size": [375, 500], "counts": "\\Sg5"}}, {"image_id": 804, "score": 0.05028878524899483, "category_id": 15, "segmentation": {"size": [375, 500], "counts": "gPg57^2"}}, {"image_id": 804, "score": 0.05028878524899483, "category_id": 15, "segmentation": {"size": [375, 500], "counts": "ePg56a2"}}, {"image_id": 804, "score": 0.05028878524899483, "category_id": 15, "segmentation": {"size": [375, 500], "counts": "TQg57Q2"}}, {"image_id": 804, "score": 0.05028878524899483, "category_id": 15, "segmentation": {"size": [375, 500], "counts": "lPg57Y2"}}, {"image_id": 874, "score": 0.8819072246551514, "category_id": 4, "segmentation": {"size": [375, 500], "counts": "_<3;m4l5b0M3M2O0O100O100O10O2O1O1O1O1O1O00O1O1O1O1O100001O1O1O1O1O2NN2O100O1O100001O1O2N3M1O2N00O1O1N1O2N2O1001O1O2N2N2O0O00N2O0N3N2O1O1001O2N1O3M1O10N001N2N2O0O2001O1O1O2N2N2N00O1O0O2N10001O02M4L4J6K5L4iMUI\\Om6d0SI\\Ok6g0SI[Oj6g0VIZOg6m2M3N2N3OM3M4L5iMWIXOn6c0WIXOn64lH`N9KL7O0T7[1jHaNj00]OLS7e1dHaN;GN8M0P7c1hHaN:KI521n6R2TIWOg6m0VIVOf6n0WIUOg6o2N11N2N4hN[IWMh6k1UIcMg0:W6Q2YJkMl5R2WJjMl5V2SJiMl5\\2PJgMl5a2mIcMm5m2aIYM[6o2\\IWM`6n2[IUMc6m2[IUMd6k2\\IVMd6g2_IWMd6d2aIZMa6T2_IoL6k0^6Q2RJmMP6P2TJlMn5R2TJmMl5S2TJmMk5U2SJmMk5T2SJnMk5U2RJnMk5U2SJmMj5V2bInL6n0V6c2gI^MZ6S2aIQM7k0Z6Q2VJlMn5P2TJoMn5n1VJnMm5o1VJnMm5o1UJPNl5o1UJoMl5Q2TJoMj5S2VJnMh5S2YJlMe5V2[JjMc5X2_JfM^5^2cJaMZ5a2gJ^M[5_2cJcM`5[2^JgMe5V2ZJkMh5R2YJnMi5P2VJPNl5o1TJQNm5n1SJRNm5n1TJQNl5n1UJSNj5m1VJSNj5l1XJTNg5k1[JTNe5k1]JUNc5i1_JUNc5h1_JWNe5b1_J]NP6Q1TJnNQ6j0SJTOQ6ORH8P2CV6NRH7n1FU61oG7m1HT61PH5m1LQ6OSH3l16j5F\\H1l1:g5EnJ<Q5DoJ=P5CPK>X8Jb[a3"}}, {"image_id": 92, "score": 0.7691575884819031, "category_id": 15, "segmentation": {"size": [431, 500], "counts": "Tfm22\\=1O1F:H8O3MC\\C3b<KaC6\\<JfC6Y<JgC6Z<HgC7[<HeC6j<0G9dM]OhGn0]7b0TGeNER1m8R3I7J2N2O1N2O3M4L4L4F9I6N1O2N2O1O1O2N2N1N2O1O1O1O1O1O1O1O2N2N2N1O2N2N3M1O1O1O2N4L2N2N2N4L2N1O2N2N3M1O0000O1002O0O1O1O00O100O1O20O1O1O01[MfJRM\\5d2SKTMo4d2ZKYMj4c2ZKPMQ5o2PKPMP5o2QKRMn4n2SKSMl4k2VKUMj4h2XKXMk4c2YKZMl4a2VK]Mn4_2TK^MP5S2_IlLb1n0S5R2]KmMe4P2]KnMg4l1]KSNe4f1aKYN`4f1bKWNa4h1`KRNf4l1^KiMj4W2X3N2K7G`0XO`0An0YOnaV2"}}, {"image_id": 92, "score": 0.759436309337616, "category_id": 9, "segmentation": {"size": [431, 500], "counts": "och21?5X<2_C3_<b0K5K4K3I8J5I8L3N2L5F9M3N2N3H7POSMUGX3e8PMnFZ3o8jLmFZ3h8j0M4O001O01O1N2N2M21O2L4M3M21M4H9B<J6NO1M4N1001N3L4N4L4L1ON3N3NdL\\Fo2c9QM_Fn2a9SM]Fk2g987I9KVIQMY3n2fLUMW3l2jLQMV3R3b3SMlEb2R:^MPFb2a3WMe27kIa2`3XMe27jI`2R:aMjE`2X::VITMV3h2jLZMT3g2lLYMQ3j2PMTMP33bI\\2W:bMmE\\2e3]M_28mIZ2c3`M_27lIZ2e3_M_2R3`MnL`2R3WMVMf2MkIg2]3^Mg2KmIg2[3_Mi2l2XMSMi2k2ZMRMh2m2n3N10O3eIiLY2Y3dMiL[2X3kLhL[M<h5n2lLbMS3^2mLiLVM<n5k2lLfL^M8i5Q3iLfLQ4[3R3O00O2O2N1N3N0000000000O2O0O2N10OO2O1O1O1N6K7I3M2N00001OM4M28H2N2N2M2N3N1N3O1N3nMlDb1g;\\O^iR2"}}, {"image_id": 1443, "score": 0.2811657190322876, "category_id": 4, "segmentation": {"size": [375, 500], "counts": "a<47l2T8=N2O1O0O1000000O10000O10000O1O11O001O001O00001O00001O0000O100000000O10000O100000000000000001O000000000000000000000000000O100000000000001O000000001N0100000000O01000000O01000000000000000000000000000000O10000O100O10O10O11O01O010O010O0001O0001O0000000O1000000O10000O11O001O001O00010O0000001OO100000000O1000000000000000000001O00000000001OO0100000O10000O10000O1001O00001O000000001O000000O010O10O0001O010O1O0101O1O001O1O001O1N1M301NhGkLo7V391N100O1O2N1O2N1O1O1001O1N2O1N2O1N2O1O0O2O00000000O2O00000O10001O0O11O001N101O00001N101O00000001O00001N101O00001O0001O0O2O001N101O1N101O0O2O00000O2O00001O0O2O001N2O2M3M3aMoFP2`9XNZFT1o9fNYF30LN7^:HTF3ePX2"}}, {"image_id": 1443, "score": 0.12929876148700714, "category_id": 7, "segmentation": {"size": [375, 500], "counts": "f<j25ZM^8Q3cGoLP8U3mGmLR8S3lGPMR8[3QH_Lg7c3VH_Lj7g3O100O2O0O100O10000O100001O1O001O1O1N101O00000000000000000000JVL^Hk3b7WL\\Hi3c7YL\\Hg3d7600000O100O100O1000000O101O000000000O10001O0O1000O100O1000000O1000SO\\HgMd7W2`HhM_7X2jHXM_OOg7h2jH`MW7`2fHaM\\7_2cHYMC1j7f2cHYMC0k7g2bHYMC0k7g2YHTM24L0i7h2YHTM24L0j7f2XHWM14MOj7f2XHXM03NOj7f2XHXM03NOj7f2WHYM12NOj7f2WHYM12NOj7f2XHXM12M0j7f2XHWM23L0i7g2ZHUM13NOh7i2bHXMFOh7i2mHUMT7k2l00O2O1aGRMS8o2lGRMS8h2eG[M7NT8m2lGSMT8m2mGRMS8m2nGRMS8m2<000\\GTM]8l2bGVM]8j2bGXM4LP8l2lGXM3M2Of7k2UHYM3N1Ng7k2UHYM3N1Ng7k2UHYM3N1Ng7k2UHYM2O2Mg7k2TH[M2N2Lg7m2THYM3N2Lg7V3VHoL3Kg7W3THPM3Ij7b3UH^Lk7f310000000000001O001O001O0001O01O00000O100000000000000000000000000001O0000000000000000000000O10O100000000000000000001O000000001OO1000O100O001O1O100O10O02O0O1000000O10001O000O1000O10O10000O100O1O010000001N1000000O1O1O1000000000000000000000000000000000001O0O1000001O00000000O1000000000001O0O1001O00001O00010O1O01O01O000O100O2O00001N2O1O00000000000000000O10000000001O2XMVG_2k8]MYGa2P9eMlFP2V9lMoFk0NYOM96AdPX2"}}, {"image_id": 536, "score": 0.8220720291137695, "category_id": 4, "segmentation": {"size": [375, 500], "counts": "b148S13nN1Oe8Z3jNfL]H`30^LU75gHj3V7=O1N2O1N2O0TI^Kc6c4ZI_Kf6a4WIbKi6f400000000O2O00000O100O1O10000000000000000000000000000O10000000000001O00000001O000000000000000000000O100000000000O1000O100000O1000000000O1000001O0000000000000000000000000000000O100000000000000000000000000000000O10000000001O000O1000000000000000000000O10000000000000000000O10000O10000O1000000O10O100000O11O0O100O100O10000O2O0000000O10001OO100000O0100000000O0100000000000O0101O000000000O10001O0000000000001O00O10000000000O10000000000000000O1001O00000O10001O000000001O0O10001O00O1000000O2O00000O1000000000000O1010O000000001O0000001O00001O001O000000O10000O2O000O10001O0O10001O00000000001O01O01O00010O10O0100O0010O0000O10000O100O10000O2O00000O10000000000001O0000001O00001O00001O001O0000O100O10000O10001N1000000O10000000000000000001O00000000001O0O1000001O00O101O0000000000000000000000000001O00001O001O001O00001O0O101O0000001O000000000000000000001O00000001O01N2O1O1O1O2N1O2N1O1O1O1O0eKPIo3Q7nKQIR4P7kKSIT4m6kKUIT4l6jKUIV4k6iKVIW4j6iKVIW4j6iKVIW4j6iKVIV4k6jKUIV4V70000O1000001N10000O10001N101N3M;E5K>Al0iNQc7"}}, {"image_id": 536, "score": 0.16550537943840027, "category_id": 20, "segmentation": {"size": [375, 500], "counts": "nld3192La1h8^NWG34OMU2\\8TNeGJKV2^8PNgGY2Y8fMgG\\2Z8`MgGa2g81001N1O01O01O0000XO[M^Hf2b7YM^Hg2Y801O\\OZMWHf2i7[MVHe2i7]MVHd2i7\\MWHd2h7^MVHc2j7]MUHe2h7^MVHc2i7`MTHb2j7`MSHc2l7^MRHd2m7]MRHc2n7^MPHc2P8b001O01O01O001O1O001O0000001O0000001N10001O001O1O1O1O001O00001O001O001O1O1O000000000000002N2N1O1O1O00000O1000000000000000001O00000000000000000000000000000000000000000000000000000000000000000000000000000000000000000000000000000000000000000000000000000001O000000000O100000000000000000000000000O10001L:EmM"}}, {"image_id": 536, "score": 0.15977072715759277, "category_id": 4, "segmentation": {"size": [375, 500], "counts": "Q25910N3O1O]86XG]3e7a0I5L2M10O001O01N10100O11O10000000O100O000O100O1O1N2O1N3O01O100O2O00O01O01O00000O010O100O1001O1O010O001O0001OO1000O10000O1000001O0000000001O00O100O100O100O1O1001O00001O0000001OO100O01000O100O1001O001O00001O00000000O100O10000O01010O01O00001O000000O10O10O1000O01001O00001O01O01O00O01000O01000O10O1010O001O01O01O0000000O01000O01000000010O0010O00000000000O100O010O100010O00010O0010O000O010O100O010O100010O0001^KRIZ4m6dKVI[4T7O0QLeHc3Z7]LfHc3Z7<0010O0O2O001001N2N4L5ZL]H<1@0d1[8TNkG30NO6KU1h9gN]F0M;0Gh9K_FNN92K_:1fEL\\:3dEM_9OjF5FN^9OkF4FM^91^FLO92LS9JlF7NOK85Je8J^G2K6Nb03]Od8L\\G3L4Nc04]OW8DnG7K4KU14mNW8DnG6Lf1OaNd8EaG3L422OH35`9JhGNgjP3"}}, {"image_id": 536, "score": 0.14210951328277588, "category_id": 7, "segmentation": {"size": [375, 500], "counts": "b?4123Kd9e0YF_O2m00QO\\9P2bFRNW9MkFY2g8hM_G^2_8eM_G_2^8aMbGa2\\8`MbGa2^8_MbGa2^8_MaGb2_8_M^Gc2b8900000001O00000000000000000000000000000000000O10000000000000000000000000000001O000000000000000000000000000000000000O10000000000000000000000000000000000001O0000000000000000000000000000000000O10000000000000000000000000000000000000O10001O000000000000000000000000O10000000000000000000000000000001O0000000O1000001O00000000000000000000000000O10000000000000000000000001O000000000000001O0000000000000001O00000O1000000000000000000000000000001O0001O0000000000000000000000000000000000000000000000O1000000000000001O00000000000000000000000000000000000000000000000000O100000000O100001O000000001O000000000000000000000000000000000000O1000000O100000000000000000000001O000000001O0000000000000000000000O10000O1000000000000O100000000001O0000000000000000001O0000000000000000O100000000000000000000O10000000000000000000000000000000000001OO100000000000000000000000000000000000000000000000000000000000000000000000000000000000000000000000000001O00000000000000O1000000000000000000000000001O000O106J2N5IoM"}}, {"image_id": 536, "score": 0.10487649589776993, "category_id": 7, "segmentation": {"size": [375, 500], "counts": "_oR31=0h:Q1UOPOmEU1n9d0F:E7@=K4K5L4M3O1O010O10O00010O01N2N2N2N101N101N1O1O1N2O1O100O10001O00000001O01O000O1O00100O1O100O1000001O000001O00O1O1O1O1O1N2O1O0110O00100O010O01O0O100O1O2N1O1O10001O1O001O1O1O0O2N2O001O001O00001O000O2N100O2O0O2O001O10O01O0010O01N101N101N2O1O1O001O001O00100O2O1N1N2O1N101O0000001O0001O1O011N001O000000O10000O100001O1O001O00001O00000000001O01O000000000000O10000000001O00010O1O001O00000O100000001O0000000000000000001O1O1O1O1O1O001O000000000O10001O0O3I6JZN"}}, {"image_id": 536, "score": 0.056077003479003906, "category_id": 4, "segmentation": {"size": [375, 500], "counts": "ca_29;JT:j1VOc0gFfMR8d2hGbM0Jg7h2UHnMi7Q3N01O1N1O2N02M20100O10001O2N3M4K3N1N2O0N30O001O000000000010O0000000000001O000000000O100O100O1O1O1N2O11O1O1O1O1O1O001O0001O00O01O1O1O1O1N2O1O010010O1O2N1O1O1O001O0000O100O1O1N2O1O1O1O11O1O1O1O2N1O10O01O0000O100O100O1N2O2N1O1001O1O1O2N001O10O0000000O2O0O2M2N3N101N101O01O100O1O100O1O01O0O2O0N3M3N1O2N2O0O2O00010O0100O010O100O01N2N2N1O2O1N1O1O2O0O1100O01000O010O100O01O0O100O100O1O2O000O1001O1O001O001O001O00000000O100000000O100001O001O001O001O001O0000O100O100O100000000001O1O1O1O1O1O001O00000000000000000000001O1O1O1O1O1O1O1O1O1O0000000O0100000O10000O3M4J;ESN"}}, {"image_id": 411, "score": 0.0516388863325119, "category_id": 7, "segmentation": {"size": [333, 500], "counts": "TcR5"}}, {"image_id": 411, "score": 0.0516388863325119, "category_id": 7, "segmentation": {"size": [333, 500], "counts": "P_R51S4"}}, {"image_id": 411, "score": 0.0516388863325119, "category_id": 7, "segmentation": {"size": [333, 500], "counts": "k^R5110U4"}}, {"image_id": 411, "score": 0.0516388863325119, "category_id": 7, "segmentation": {"size": [333, 500], "counts": "TcR5"}}, {"image_id": 411, "score": 0.05109706521034241, "category_id": 5, "segmentation": {"size": [333, 500], "counts": "TcR5"}}, {"image_id": 411, "score": 0.05109706521034241, "category_id": 5, "segmentation": {"size": [333, 500], "counts": "TcR5"}}, {"image_id": 411, "score": 0.05109706521034241, "category_id": 5, "segmentation": {"size": [333, 500], "counts": "TcR5"}}, {"image_id": 411, "score": 0.05109706521034241, "category_id": 5, "segmentation": {"size": [333, 500], "counts": "k^R5110U4"}}, {"image_id": 411, "score": 0.050705913454294205, "category_id": 18, "segmentation": {"size": [333, 500], "counts": "TcR5"}}, {"image_id": 411, "score": 0.050705913454294205, "category_id": 18, "segmentation": {"size": [333, 500], "counts": "TcR5"}}, {"image_id": 411, "score": 0.050705913454294205, "category_id": 18, "segmentation": {"size": [333, 500], "counts": "TcR5"}}, {"image_id": 411, "score": 0.050705913454294205, "category_id": 18, "segmentation": {"size": [333, 500], "counts": "k^R5110U4"}}, {"image_id": 411, "score": 0.050326284021139145, "category_id": 13, "segmentation": {"size": [333, 500], "counts": "i^R56U4"}}, {"image_id": 411, "score": 0.050326284021139145, "category_id": 13, "segmentation": {"size": [333, 500], "counts": "n^R57o3"}}, {"image_id": 411, "score": 0.050326284021139145, "category_id": 13, "segmentation": {"size": [333, 500], "counts": "TcR5"}}, {"image_id": 411, "score": 0.050326284021139145, "category_id": 13, "segmentation": {"size": [333, 500], "counts": "TcR5"}}, {"image_id": 411, "score": 0.05028878524899483, "category_id": 15, "segmentation": {"size": [333, 500], "counts": "TcR5"}}, {"image_id": 411, "score": 0.05028878524899483, "category_id": 15, "segmentation": {"size": [333, 500], "counts": "j^R55U4"}}, {"image_id": 411, "score": 0.05028878524899483, "category_id": 15, "segmentation": {"size": [333, 500], "counts": "o^R56o3"}}, {"image_id": 411, "score": 0.05028878524899483, "category_id": 15, "segmentation": {"size": [333, 500], "counts": "TcR5"}}, {"image_id": 94, "score": 0.6622419357299805, "category_id": 7, "segmentation": {"size": [376, 500], "counts": "_l]2Q64TJY5X6M2O0000000000000000000000001O000000000000000000000O100001O00000000000000000000O10000001O0000000000O10000000000000000001OO1000000000000000000000O1001O00000000000000O100000000000000000000000000000000000000000000000000000001O0000000000O0101O0000000XNkJeKLl0Y5^3lJdKOl0U5`3mJbK0m0S5`3oJaKOn0S5a3PK]K1P1o4b3aKZL`4b3fKYL]4e3fKlKPON\\5U4fKkKROK[5Y4dKjKh4W4XKgKi4Z4[12M1QJbKc4^4\\KcKd4\\4\\KdKe4Z4^1N5I5L3B\\HfLe7k2ZHUM5Mc7m2YHTM5Ob7m2ZHSM40c7l2iHRMZ7n2k0NaGSMQ8k2mGYMR8[2iGdM60S8X2n0L4G:I6H7VOlEH^:BhE80LPX_1"}}, {"image_id": 94, "score": 0.19823914766311646, "category_id": 4, "segmentation": {"size": [376, 500], "counts": "geP22d;3L4J7L3N1N3O1N2O2M>B4M3aG`N_6d1RITOa6T1PIXOAQOg6k1oHL4^Nj6j3QI[L<BQ6h4eIbKX6S5L8H7I5L2M2M3M2N2N2N1O2N2N11000O2O8H4K10000N1O1O1O1O1O100O11O001O000010O00000O100O1O100O11O00001O00001O00O100O1O1O1O1O1001O001O001O000000O100O1O1O1O1O11O1O1O1O1O1O1O0000O100O1O100O1001O1O1O1O001O000000O100O100O100001O001O1O001O0000O10000O100O1001N101O1O001O1O0000O100O100O100001N2O001O1O1N2OO10O100O010O1N2N3M3M2O2M3C=K4M4M3N1O2N2N101O1N2N4L4K7_M\\JQNXO@P74j``1"}}, {"image_id": 1405, "score": 0.0516388863325119, "category_id": 7, "segmentation": {"size": [375, 500], "counts": "\\Sg5"}}, {"image_id": 1405, "score": 0.0516388863325119, "category_id": 7, "segmentation": {"size": [375, 500], "counts": "\\Sg5"}}, {"image_id": 1405, "score": 0.05109706521034241, "category_id": 5, "segmentation": {"size": [375, 500], "counts": "\\Sg5"}}, {"image_id": 1405, "score": 0.05109706521034241, "category_id": 5, "segmentation": {"size": [375, 500], "counts": "\\Sg5"}}, {"image_id": 1405, "score": 0.050705913454294205, "category_id": 18, "segmentation": {"size": [375, 500], "counts": "\\Sg5"}}, {"image_id": 1405, "score": 0.050705913454294205, "category_id": 18, "segmentation": {"size": [375, 500], "counts": "\\Sg5"}}, {"image_id": 1405, "score": 0.050326284021139145, "category_id": 13, "segmentation": {"size": [375, 500], "counts": "\\Sg5"}}, {"image_id": 1405, "score": 0.050326284021139145, "category_id": 13, "segmentation": {"size": [375, 500], "counts": "\\Sg5"}}, {"image_id": 1405, "score": 0.05028878524899483, "category_id": 15, "segmentation": {"size": [375, 500], "counts": "\\Sg5"}}, {"image_id": 1405, "score": 0.05028878524899483, "category_id": 15, "segmentation": {"size": [375, 500], "counts": "\\Sg5"}}, {"image_id": 792, "score": 0.08345472812652588, "category_id": 4, "segmentation": {"size": [327, 500], "counts": "aP1363`9>[FBR9NPGj0a0SOh7V1VHlNGO\\71bHV1NjN41M1^7OaHV1OkN31M0_71_HU10kN31NO^71`HU10kN41LO`7h1cHYNMO`7h1bHcN^7^1aHbN_7T2N10000O2O0O3N1N101O0O2O000O100O2M2O1O1O2O000O100000^OVIaM0Jc6N`Ig2M`M1Kb6O^Ig2O_M2Ja61]IZ20kM101J`6b2_IcM011J`6b2_IcM011J`6b2_IcM011J`6b2^IdM100Ka6m2^I_Mb6a2^I_Mb6a2^I_Mb6S300000000000O100000000000O1000001O000000000000001OHaIhL_6X3aIhL_6X3bIgL^6Y3bIgL]6Y3dIgL\\6Y3dIgL\\6Z3cIfL]6Z3cIfL]6Z3cIfL]6Z3bIgL^6Y3bIgL^6Y3bIgL^6a3000000O100000O1000O10000001O0001O0000000000000000000000000000000O1000000O1000000O1000000000001O00000000000000000000000001O000000000000O10000000000000000000000O10000001O0000000000001O000000001O000000000000000000000000000000000000001O0000000000000000000000001O000000000000000000000000O100000000000000O10000000000001O00000000000000001O00000000000000O10000O10000O10000O1000000O100000000000000001O00000000000000001O0000O10000O10000O10000O10000O10000O1000000001O0000000000001O000000001O00000000O100000000O10000000000O10000000000001O0000001O000O2O00001O00001O000O11O0000000O10000000000000001O00000000000000O1000001O00000000001O0000001N1000001O000000000000001O000000000000001O00001O001B]IVMc6i2_IVMb6h2_IXMc6f2^IYMc6e2^I[Mc6d2^I[Mc6d2]I\\Mc6c2_I\\Mb6c2^I]Mb6c2_I\\Mb6c2^I]Mb6b2`I[Mb6e2`0O100O10000O1000000O10000I`HgM`7X2bHgM^7Y2cHfM]7Z2cHeM^7Z2dHeM]7Z2801O0O2O005J4M2N1GgGaN\\8]1eGbN]8\\1eGbN\\8\\19O1O001N10001O0000001O001O001O1O001O1O1O001O1N4M3DeFEb93aFLb90aFMoU1"}}, {"image_id": 792, "score": 0.0516388863325119, "category_id": 7, "segmentation": {"size": [327, 500], "counts": "U]o44S8"}}, {"image_id": 792, "score": 0.05109706521034241, "category_id": 5, "segmentation": {"size": [327, 500], "counts": "U]o421O000000l7"}}, {"image_id": 792, "score": 0.050705913454294205, "category_id": 18, "segmentation": {"size": [327, 500], "counts": "\\eo4"}}, {"image_id": 792, "score": 0.050326284021139145, "category_id": 13, "segmentation": {"size": [327, 500], "counts": "T]o4j0^7"}}, {"image_id": 792, "score": 0.05028878524899483, "category_id": 15, "segmentation": {"size": [327, 500], "counts": "T]o4i0_7"}}, {"image_id": 101, "score": 0.0516388863325119, "category_id": 7, "segmentation": {"size": [375, 500], "counts": "\\Sg5"}}, {"image_id": 101, "score": 0.0516388863325119, "category_id": 7, "segmentation": {"size": [375, 500], "counts": "\\Sg5"}}, {"image_id": 101, "score": 0.05109706521034241, "category_id": 5, "segmentation": {"size": [375, 500], "counts": "Ukf5;l7"}}, {"image_id": 101, "score": 0.05109706521034241, "category_id": 5, "segmentation": {"size": [375, 500], "counts": "fkf57_7"}}, {"image_id": 101, "score": 0.050705913454294205, "category_id": 18, "segmentation": {"size": [375, 500], "counts": "\\Sg5"}}, {"image_id": 101, "score": 0.050705913454294205, "category_id": 18, "segmentation": {"size": [375, 500], "counts": "\\Sg5"}}, {"image_id": 101, "score": 0.050326284021139145, "category_id": 13, "segmentation": {"size": [375, 500], "counts": "Wkf5;j7"}}, {"image_id": 101, "score": 0.050326284021139145, "category_id": 13, "segmentation": {"size": [375, 500], "counts": "dkf5:^7"}}, {"image_id": 101, "score": 0.05028878524899483, "category_id": 15, "segmentation": {"size": [375, 500], "counts": "Xkf553Lh7"}}, {"image_id": 101, "score": 0.05028878524899483, "category_id": 15, "segmentation": {"size": [375, 500], "counts": "ekf58_7"}}, {"image_id": 733, "score": 0.06402277946472168, "category_id": 11, "segmentation": {"size": [418, 500], "counts": "cX2o0S9SOXIc1PN]NV85aHg2PO\\M>G_76nHj2VOZM;Ha75dHQ3@RM:J3Ln6;mHo2JPM6L3LQ79hHQ3NnL5N2LS78eHQ31mL5N1NS77eHP32mL5N0O4K_6<TIP34mL3O1N3MR6KnIm3J^L2O1N2OQ6KoIk3K^L2O0O3Oo5LPJi3L^L2O0O202H`53^Ji3L^L2O00101Ha54^JW3HQM5M2O0011NJc51_JW3HQM5M2O0011MKc52_Je3N^L2O0O21NL`53^Jf3O\\L3O0O3ONN_55[Je31\\L4N1M30NO]5Z4]JmK3M3L30M0]5[4\\JlK4L4L30M1[5\\4\\JlK4L6I40L3Z5]4[JkK5L7G5OL7V5j2fJgNLbNZ1MS4i2kJfNHcN[1NQ4Z2dJgM9^1GcN\\1Mo3[2hJeM6a1FbN]1Mn3[2kJcM6b1DbN^1Nm3[2jJeM5a1FaN^1Nm3]2fJeM8a1DaNa1Lm3m2lJTOW1nMn3P3gJTO[1lMn3R3cJTO`1hMn3c5bKZJ]O1R5e5`K\\J^ONR5e5aK_Jo4a5PKaJo4^5QKeJm4[5SKfJl4Y5TKjJj4V5VKkJj4T5VKlJj4T5VKkJk4U5VKiJk4X5TKgJm4Y5TKdJo4\\5PKcJQ5]5PK`JR5`5oJ]JS5W5nIoJ`1KP4T5bJPK]1MQ4R5dJPKZ10Q4o4fJQKY10Q4o4fJQKY11o3o4hJPKY10o3R5fJPKZ1No3T5eJoJ\\1LP4V5bJoJ`1Hn3i5_KdJf4\\5XKgJf4\\5WKeJi4]5UKcJj4b5QK_Jo4d5mJ]JS5e5jJ\\JV5e5iJ[JV5g5hJZJX5g5hJXJX5i5gJWJZ5h5gJWJY5j5fJVJZ5j5gJTJZ5l5hJRJX5o5kJlIV5T6PKdIR5\\6k0O011@\\I^Jd6b5\\I^J`6U6N2N2N101TJ`IS5b6`JlI^5m6O001O000000001O001O1O001O1O1O001O001O000O100000000O100000000000001O001O00001O0000001O000000001O0O101O000000aMUKgLk4X3VKhLj4W3XKiLg4V3ZKjLf4W3YKiLg4W3YKhLh4X3XKhLh4Y3VKhLj4X3VKgLk4Z3TKfLl4h50UNVK]Kk4a4\\KZKd4d4bKWK_4e4fKYK[4d4iK[KW4d4jK[KW4g4fK[KY4h4cKYK]4k4^KWKa4k4WK\\Kh4_601ObMTKfLl4X3VKhLj4g2TK\\K3m1h4f2XKZK1P2f4f2[KYKOQ2f4e2]KXKNS2e4e2]KYKMR2g4e2YK[K0P2g4g2VK[K2n1h4X3XKgLi4Z3VKfLj4Z3UKgLk4Z3TKeLm4[3SKdLn4\\3RKcLo4g52O0O1O100000O10000000O100O1M300000PKXHf4h7YKYHg4Q800000000001O0000000000000000000000O1000000000000010O0000001O0000001O010OO1000000000000O1000000000000000O1`KTKj0l4SO]Kg0c4hNXKXM9o3_4hNPLW1Q4gNRLX1n3gNSLY1m3YNRKnMR1i3l3WNVKnMo0i3l3YNWKkMn0l3k3XNYKkMl0m3k3XNYKjMm0n3j3XNZKiMk0o3l3XNZKhMj0P4l3XNaLi1_3WN`Lj1`3VN_Lk1`3VN^Ll1b3TN\\Ln1d3RN[Lo1e3QNYLP2h3PNWLQ2i3oMVLR2j3nMVLR2j3nMXLP2i3oMXLP2h3`MnJdN]1k3d3aMPKcN]1k3d3aMoJdN^1j3c3aMQKdN]1j3d3`MoJeN_1j3b3aMPKdN_1k3a3[LlJd04VO`1j3a3ZLmJe02WOa1i3`3ZLoJd02XOa1h3_3ZLoJf01XOb1g3]3]LoJd02XOa1h3^3]LmJd04WO^1k3`3\\LlJd04VO_1j3a3bMPKdN^1k3`3cMRKbN\\1l3c3bMQKbN[1m3c3cMPKaN;G`0W4U4aMoJbN;H>V4X4aMoJaN:K5[4b4ZMmJaN;MO]4i4XLmJ;;ROJ]4n4VLoJ:8R4i4dKoJ;6Q4l4eKlJ;9o3k4fKlJ;9SOH]4T5_MUKQNK^4P5aMUKPNN]4m4dMUKlM1_4j4eMVKjM3_4g4gMWKgM5a4d4hMoKS2Q4mMTLn1m3QNTLn1l3RNULm1k3SNULl1l3TNULk1k3VNTLj1k3WNULi1k3WNULi1k3WNULj1j3WNULi1j3XNiKdM^OT4i4XNhKfM^OR4j4YNTKdM82J:HU3R5kNPKiM:OK6NT3m4oNlJlM<LM42JJm2o4IWK^MM1a0f2Z4MWK\\MN0c0f2X40TK\\M0Nd0f2Y41oJ_M0Mg0c2Z4U1dKmN[4T1aKoN_4S1\\KPOe4Q1XKQOg4Q1VKPOj4R1SKSLK\\2R5a1RKRLN\\2P5b1QKSLO[2Q5b1oJRL2\\2n4b1PKRL2\\2o4a1oJSL2\\2P5`1nJTL2\\2P5`1nJTL2\\2Q5_1mJUL2[2R5`1lJUL2[2S5_1jJWL3Y2T5`1iJWL3Y2T5`1iJWL3X2V5X1nJaLKX2W5c0hJTM63JU2Z5a0iJUM4JMX2LkM[5^2dJdM7N2J05Kc11[NY5_2eJcM501L12MS1IQO:HU5b2fJbM500N02N6F<7]On5\\2UJbM41c0N^O1I?a6l1WJbMU1<k4n1[LjMl3S1kHVO4Ij:5UE06Inhi1"}}, {"image_id": 733, "score": 0.0516388863325119, "category_id": 7, "segmentation": {"size": [418, 500], "counts": "XS\\6"}}, {"image_id": 733, "score": 0.05109706521034241, "category_id": 5, "segmentation": {"size": [418, 500], "counts": "XS\\6"}}, {"image_id": 733, "score": 0.050705913454294205, "category_id": 18, "segmentation": {"size": [418, 500], "counts": "XS\\6"}}, {"image_id": 733, "score": 0.050326284021139145, "category_id": 13, "segmentation": {"size": [418, 500], "counts": "XS\\6"}}, {"image_id": 733, "score": 0.05028878524899483, "category_id": 15, "segmentation": {"size": [418, 500], "counts": "XS\\6"}}, {"image_id": 35, "score": 0.5856712460517883, "category_id": 11, "segmentation": {"size": [375, 500], "counts": "Y33b0NN6L0h1=SNI6Fn3W8PO4N0O10001O000000000O1000000001O000000O10O10001O01O000000O001010O0100OO1O01O0020O01000O0O00010O02000001NN2O0010O10100O10O0O1O010O11O1O101NO1O1O0011O1O2N2N1OO100O1N22N1N2O0O1001N1O11O2UHbLX7`3eHgLa6FhIf3DjL9F]51aJa3IiL7Hd46UKM3^3LgL:Fi41PK31_3LeL>Cj43lJ7N_3NbLQ6FTJ:K_30_L5K]5LeJ;Gb3NbL2Ia5O`J61j4R5gKoJj3KeK8FX4o0eKe3MfK3IT4Q1mKS4OlJR4T1nKQ4NlJU4R1kKa4W4^12OAmH[LS7h3SISLi6l3WIULk6h3UIYLf0LT5f3VJ^Le0NX5R3iITM;Lf0K^5i2_J[Mk65XHh1S1QNX7i1kHUN`7]1e\\[4"}}, {"image_id": 35, "score": 0.2050630897283554, "category_id": 20, "segmentation": {"size": [375, 500], "counts": "d1k05l5i3`1A4M000000001O0O2O0000001O000000000000000000000000000000000000000000000000000000000000O100000000000000O100O11O00001OO100O1O11O1O001OO1O2N1YIdLR5]3e1O1O1O10hHkLk5W3lI[Mh5i2oI`Mm5d2nI_MP6e2mI]MR6U40101NN\\OgJjJY5V5mJbJV50gJn4:jJR58gJ]4O`Km52SJ^4\\6aKcI^4`6_KaI`4h608IHeK\\IR4j6QLUIl3l6ULUIi3l6WLTIi3l6WLTIh3m6WLTIi3m6VLSI[3FnLW7FTI\\3FlLX7GSI\\3EnLg7R3YHnLh7Q3XHoLh7OXHd2O]Mk7KZHU3^6mLZJL[OU3[6YMRJ_OF<EY2f6fMcJOkNV2g6aMgJ7dNl14lMV86gG^1HgN=FT83iG7He06UO6LU8OjG8J3MN9G]90fF1]l]4"}}, {"image_id": 35, "score": 0.08238894492387772, "category_id": 11, "segmentation": {"size": [375, 500], "counts": "_=a0?o0C88fNJT1W4Q6Dn0TO4M2N200O100O100ObGVMQ8j2>1O000000000000000001N10000000000001O01O01O001OO1O010O100O10O10010O001O010O0000O010O1000O010O11O01O01O01O001OO10000O10O10000000001O001O1O1O0000O10O01000O011O00001O001O1`IoL]N1V5P3\\LRM[N0X5n2\\LSM\\NOU5Q3`LoLZN1R5S3eLlLYN1a43XKP3P2iLYN3^49UKl2e2lLV29SKl2f2lLV29TKj2`2TM\\23SKi2_2UM_22RKi2\\2YMb2X3UMRMj2n2RMUMo2k2PMVMQ3i2nLXMV3d2hL^MY3a2fL_M[3`2eLaMZ3WOnJi2i1PN[3VOkJj2i1PN`3W2aLjMc3Q2]LoMd3P2\\LQNe3m1[LSNf3m1ZLRNg3m1ZLSNf3n1YLSNh3l1XLTNi3j1WLXNh3i1WLWNi3j1VLWNi3i1XLWNf3i1ZLYNe3f1\\LZNc3f1\\LZNd3f1]LXNe3g1[LZNe3d1[L]Nf3b1[LZNi3e1WL^MWN8i5[2PL[M[N6g5_2nK[M[N6g5_2oKXM\\N9e5_2^LaMoMDV5k2iLcMkMH;L[4i2^MTNRN[O[4c2_MVNRN\\OJJV4d2lMZNoMJR4l1oMYMSNj1l3m0RNUMVNm1h3m0fNoNZ1P1kNeMSMd0R4f1mNdMSMd0Q4g1nNcMSMe0o3h1oNaMSMf0o3i1oN_MTMg0m3i1PO`MTMd0n3l1nNaMRMj0j3e1TOcMnLP1h3]1ZOYO`0g0_O\\O?d0A^O=b0C_O<a0DA9a0FA8>IB8=HC8=HC8=HC8=HCSMgMj2f23CPMkMl2b24CoLlMm2a240K051JO62IN66FL98CH=g0SOZOm0l0mNUOQ1n0lNSOU1l0kNSOV1l0kNTOV1j0lNTOU1i0nNWOS1e0PO[OQ1b0RO\\Oo05mL[MU2`2o03oLZMS2c2n03oLZMS2c2m05lL\\MV2`2m0c0QO^Oo0d0oN]Oo0h0lNYOT1j0hNXOV1j0iNWOV1j0^MWLh0Q3i1j0]MWLi0o2j1k0[MWLk0n2j1k0ZMXLk0n2j1l0YMWLm0m2j1n0UMWLQ1k2i1]1VNcNj1]1UNdNk1]1TNdNk1[1UNgNj1W1WNkNi1l0_NUO`1c0gN_OY18nNJQ14PONo0XNYMNh1l1o0TN[MjNO`0g1d2m0MRO4l00RO0l06oNKo09kMWL`0a3`1=mMWL`0^3]1`0QNUL`0^3Y1a0UNSLNL4c3b1a0[NdLOR3Z1Y6]Oj0[OX_V3"}}, {"image_id": 1400, "score": 0.161251500248909, "category_id": 4, "segmentation": {"size": [333, 500], "counts": "_f>d1U8T1QO[MSIk25SMU6]3dIhLZ6g3N2N1O2O0O100O100O1O1O100O100O10000O2O000O100O100O100O1O100O1O1bJ_KP5a4PK_Ko4b4PK`Ko4`4PKaKo4`4QK`Ko4a4PK`Ko4`4QK_KP5a4PK_KP5a4PK_Ko4b4QK^Ko4b4RK\\Ko4e4PK[KP5e4QKZKo4f4QKZKo4f4;101O000O101O000000O10000000000O10gJXKm4h4SKXKm4h4RKYKn4g4RKYKn4g4QKZKo4f4QK[Kn4e4RK[Kn4e4RK[Kn4e4SKYKm4h4SKXKm4h4TKWKl4i4;10000O10000O1000000000000010O00001O010O001O_J^KW5l400010O000000O10000O10EkJ^KT5c4nJZKS5f4oJXKP5i4RKUKn4j4UKTKj4m4;0O10000O020O001O0gJVKP5T5O00010O01O00010O001O0000O100O100O100O10000O10000O100000001O01O01O01O01O01O00100O001O0010N100O100O100O2O000O101O0O101O0000001O0001O00010O00001O1O001O0001O000O101N100O2O0O101O0O2O000O2O000000010O000001O00001O001O001O001OO101N1O100O100O100O101O0O10000O1001O000000001O0000001O00001O001O00O10000O100O2O000O10000O10000000000000000001O0000001O0000001O000000000000O1000000000000O1000000000000001O001O001O001O001N2O001O001O0000O1000001O0000000000000000000000000001O0000000000001O0000000000000000001O000000000000001O0000001O001O001O001O1O001O1O001O1O001O000000000000000000000000000000000O101O1O001O2N1O1O2N1O2N1dLgJb1Y5]NkJ`1V5^NnJ_1R5`NQK^1P5`NSK^1m4bNSK^1m4aNTK^1m4bNSK^1m4aNTK_1l4aNTK_1l4`NVK^1k4bNUK^1k4XN_Kh1a4WN`Kh1a4XN_Kh1a4XN_Kg1c4XN]Kh1c4XN]Kg1d4YN\\Kf1e4ZN[Ke1f4[NZKe1f4ZN\\Kd1f4YN]Ke1e4YN^K[OnNm1f5YNTJ0i1l0ZN[Ol5C\\JNc14WN=3KT9FRG2h>"}}, {"image_id": 707, "score": 0.0516388863325119, "category_id": 7, "segmentation": {"size": [375, 500], "counts": "blf5154N0O14M`5"}}, {"image_id": 707, "score": 0.05109706521034241, "category_id": 5, "segmentation": {"size": [375, 500], "counts": "ilf541:2HN010000=4_Om3"}}, {"image_id": 707, "score": 0.050705913454294205, "category_id": 18, "segmentation": {"size": [375, 500], "counts": "\\Sg5"}}, {"image_id": 707, "score": 0.050326284021139145, "category_id": 13, "segmentation": {"size": [375, 500], "counts": "Rlf5[3o3"}}, {"image_id": 707, "score": 0.05028878524899483, "category_id": 15, "segmentation": {"size": [375, 500], "counts": "Wlf5i23[MR4"}}, {"image_id": 1399, "score": 0.7486929297447205, "category_id": 5, "segmentation": {"size": [375, 500], "counts": "R_=1_;d0cD@d:l0L5O00000M3O1O100O1N200000000O1000000O10000000000O10000001OO100001O00O0011O2NO1O10N4L3N1N2JaESOa:l0_ETOe:f08L3M7I:Gike4"}}, {"image_id": 1399, "score": 0.32820141315460205, "category_id": 4, "segmentation": {"size": [375, 500], "counts": "hg<5\\;7N1kDDf81ZIc0e6_OUIf0j6\\OTIe0l6ZOTIh0j6YOSIj0m6WOPIk0P7VOnHk0R7VOmHj0S7VOkHl0V7SOhHo0X7QOgHP1Y7oNgHR1X7nNiHR1X7lNiHT1Y7iNhHW1X7iNhHW1k810000000000O1O100000000O100001OO1O1O11O1O00O100001O001N2O1N1O2O1N2J^EUOd:h06O2O2J9J4Kfhd4"}}, {"image_id": 1399, "score": 0.3148948550224304, "category_id": 16, "segmentation": {"size": [375, 500], "counts": "kj=5[;8K5kDCm:c01N12N3M2N1M3001O00N3M4NO1O1001O0O0O12O2NO1N1101N3MO2O10O3N00N1011O3MO0O2O03K5J31N20N7Fgg0FkWf4"}}, {"image_id": 1399, "score": 0.0813053548336029, "category_id": 6, "segmentation": {"size": [375, 500], "counts": "TS=150U;0jDd0O\\Oe:o0N3M2O0O2M2M30002M1O1O1O2O000O01001O0O00020O000O01O100000O0100000000O1000000O1O10002M1O2N2O0O2M4L3N3L7J2K5BkD2`;012_hd4"}}, {"image_id": 1399, "score": 0.07369768619537354, "category_id": 15, "segmentation": {"size": [375, 500], "counts": "^]d01f;00000cm21]RMO]D0[;1dDO10\\;4cDL\\;5dDK\\;1cD11N[;64K`D0a;0`DO`;041O0]DO`;041\\DO`;1`DO_;51L`DOd;0`fg4"}}, {"image_id": 593, "score": 0.07696910947561264, "category_id": 5, "segmentation": {"size": [375, 500], "counts": "]WQ3S1Y:TOhER1P9kNVG2O2La1j8_NVG3Ok1k9D4LL8oNP1K52K<EH8E<L41N2NN3I6M33M1OO1L5N13L3N00L4O22L3N00L4O13M3MO0O1O24L3NN0O1005M1N0OO11O4L4MOO1O2N5K6H5M3L5L5IR1fN]E@Vlo1"}}, {"image_id": 593, "score": 0.07627929747104645, "category_id": 9, "segmentation": {"size": [375, 500], "counts": "hlS3260_:OjE2D21O1NV:m0fEWO2NP:b1NO2F`0Ce0@[OCcEm0[:VObEQ1X:POfES11kNQ:b10M2O2NO3N3M2M20001O2M0000001O2N2O1N10O1O100001N2O00O1O10O101O2N00O0O110001O1O1N01N2O11O002N00O1O001010O2N1OO2M2O101O3M2L30O1OJWF^Ni9a1YF^Ni9_1ZF^Nm9W1j0jNXE3L31K[;O`me1"}}, {"image_id": 160, "score": 0.9996365308761597, "category_id": 7, "segmentation": {"size": [375, 500], "counts": "U=17h1]9]N]Fg15UNm81QGS2OnMo81PGS2OmMP92PGW2i8eMZGd2e8]MYGd2f8^MYGb2g870000O100000000O1000000O10000000000O10000000000O10000000000000000O1000000000000000000000000000000001O00000000O100000000O100KlLgGT3Y8500O10O100000000000000000000000000001O000000000O10000001O00000O1000000000000O10000O101N100000O2O0000001O000000001O000000000000000000O10000O10000O1O100O100O1O100O11O001O001O001O0000001O000000000O2O00O2O0000000O100O100O1O100O100O1\\O\\GUNd8k1\\GTNe8l1\\GSNd8m1[GTNe8l1[GUNd8_201O001O1O1O001O1O001O000O2O000001N10000O10000O1O100N2O1O1O1]O[GTNe8l1\\GRNe8n1[GRNe8n1[GRNe8n1[GRNe8n1ZGSNf8`2O001O1O1O2N1O1O1O001O00001O0000O10000O1O1GcGWM^8e2iGWMX8[2bGlMk8S2WGkMj8U2WGgMl8X2VGfMk8Z290000000000O001O10000O100000000000000000_GiMb7W2^HiMb7Q2aGSNm0Lb7P2bGTNl0Ma7o1cGTNl0Lb7Q2aGSNm0Lb7Q2aGSN^9m1bFRN_9n1bFQN^9o1bFQN^9o1cFPN]9P250000000000000000000000O1O10000O100000000O100KXF[Nh9e1YFZNg9e1[FZNe9f1[FZNe9f1[FZNe9f1\\FYNd9g1\\FYNd9g1600000001O00000000000000000000000O100000000O10000000000O100000000KnEeNS:^11O1O10001O00001O0000001O00001O000000001O000000SGgN\\7Y1dHgN\\7Y1dHgN\\7Y1dHgN\\7Y1cHiN]7V1cHjN]7V1cHjN]7V1cHjN]7V1cHjN]7V1cHjN]7V1cHjN]7V1cHjN]7V1[HgNQO4c8U1dHkN\\7U1dHjN]7V1cHjN]7W1bHiN^7W1bHiN^7W1bHiN_7W1`HiN`7W1`HiN`7Y1^HgNb7[1\\HeNd7\\1[HdNe7\\1[HdNe7\\1[HdNe7\\1[HdNe7]1ZHcNf7]1ZHbNg7^1ZHaNf7_1ZHaNf7^1ZHcNf7]1ZHdNf7Z1[HfNe7Y1\\HgNd7Y1\\HgNd7X1]HhNc7W1^HiNb76TG`03WOW14c73UG8OE`10\\73UGOONi11R72WGM0Nh13Q71XGMo12j60WGNo12j60XGLo14i60XGLo14j6OWGMo14j6OWIMoM4j8OWIMoM4j8OXILnM5j8N_I2a6N_I2b6M]I3d6L]I4d6K\\I5R91O1ZNI_F0T16^8K]F0T15^8L^FOS16e7IjG2]O0T15e7IbG0F2O0T14f7JaG0F2O10Ml06n7JaG0F3N01Nk04P8K`G0F3N01Nd0O\\O5k8K`G0F3N00Oe0N\\O5k8K`G0F3N00Oe0N\\O5k8K`G0F2O10Nd0O\\O5e9M[F01Nk05j8L[F0S15a8J]F1R15a8JiG7j91O1OJfD2X;NjD1V;OjD1V;OjD1V;OjD1V;OjD1n:LUE3M1n:MTE2N2m:LUE2N2m:LUE2N2m:LUE2O1l:MUE2O0m:MUE2O1U;NkD2U;NlD0^;01OU^="}}, {"image_id": 160, "score": 0.8056422472000122, "category_id": 4, "segmentation": {"size": [375, 500], "counts": "^<:166NNm1_7l1[OkK_IW4_6mK\\IW4b6kK[IW4c6lKZIU4e6`0O1O1O00O101O001O001O1O1O1N101O00001O0000000000010O000001O0001O01O00010O00010O0001O00001O010O001O001O001O010O1O00O100O2N1O1O1O1O100O10001N10000O10000000001O0000010O00001O00[K[IY4d6fK]IZ4c6eK_I[4`6dKaI\\4_6cKcI\\4]6dKcI]4\\6cKdI]4\\6cKdI]4\\6dKbI^4^6bKaI^4_6cK_I^4a6<0001O000000001O00000000001N1000000O1000001O0O1000000000001O00001O001O2N3M4L1O1O0O2O00001O0000001O000000000O2O0000001O00000O2O00001O00000000O101O00000000000000001O00000000000001O000O2O00001O001O00001O001O000000001O0000001O0000001O010O001O001O00001O00001O00000O10001O0000000000001O01O000000000001O0000000000000000000000000000000000000000000000000000000000000000000000000000000000000000000000000000000000000000000000000000000000O10000000001O000000000000000000000O1000000O10000O10O01O100O1O1O10000O101O0O10000O1000000O2O000O1000000O10000O100O10000O10000O10000O100000000000000000000000001ATJQKl5n4VJQKj5o4VJQKj5n4XJQKh5o4XJPKi5P5XJoJh5P5YJPKg5P5YJPKh5o4YJPKg5P5YJPKg5P5ZJnJh5Q5XJoJh5P5ZJoJf5Q5[JmJg5R5YJnJg5R5ZJlJg5T5?O0O10001O0O101O001O001N2O001O1O001N2O1O001O001O0O1000001O00000000000ElHSLT7m3oHPLQ7o3QIPLo6P4RIoKn6P4SIPLm6P4TIoKl6Q4TIoKl6P4UIPLk6P4VIoKj6Q4WInKj6P4?01N2N101N2N5_OVHlLQ8m2?M2O1N2_OUGSNm8k1VGSNj8m1WGQNk8m1WGQNj8o1WGPNj8n1WGRNi8n1XGQNh8o1XGPNi8o1YGPNg8`1nFkN;Eg8`1nFkN<Df8`1PGjN;Eg8`1oFjN:Fg8_1PGjN;Fe8`1QGiN:Ge8_1SGiN_9V1aFiN`9V1bFiN_9V1bFhN`9V1bFiN^9W1cFgN_9W1cFhN^9W1c0M3M7Gch1"}}, {"image_id": 160, "score": 0.5659988522529602, "category_id": 7, "segmentation": {"size": [375, 500], "counts": "b=36OKd11\\N^93cFk1\\99dFiMV9X2hFiMX9\\2O0O10001O000000000lF`MQ9`2nFbMQ9b20000000000001O000000000000000000O10000000O1000000000000O1000000001O0000000000000001O0000000000000000O100000O100000000O10000O100000000001O00010O001O00001O000001O000000000000O1000000000000000000O0100000000000001O00000000000000001O0000000000000000O100000000000O100000O10000000000001O00000000000000001O00000000000000000000O10000000000000000O1000001O0001O0000000001O0001O000000000bMmFX2T9gMlFY2T9gMlFY2S9hMmFX2S9600000000O100000000000000OlMoFd1Q9\\NoFc1R9]NoFb1Q9^NoFb1Q9^NnFd1R9[NnFe1R9[NnFe1R9[NnFe1R9`00000001O0000000bMmFX2T9gMlFP104T9lNmFo0ORO0m0T9ROmFo0ORO0m0T9ROmFo0ORO0m0T9ROmFo0ORO0m0T9ROmFo0ORO0m0T9ROlFP11POOn0S9SOmFo01POOn0S97oFkNNn0S97oFjNOo0R9\\OmF<3XOOo0Q9]OmF70^O4NOP1P9\\OoF7O^O8o0i8]OPG0NF>m0d8]OPGNd0d0\\8^OPGLg0e0Y8_OPGLg0e0Y8_OPGGNNj0l0X8[OnFI210Nh0m0X8ZOoFI22ONi0l0W8[OPGH13ONi0l0V8\\OQGG22NOi0l0W8[OPGH22ONh0m0W8[OVGJh0k0R8[OVGJh0k0R8[OVGJh0k0R8[OVGJi0j0Q8\\OVGJi0j0Q8]OUGIj0j0R8\\OTGKi0i0S8\\OUGJi0i0R8ZOmFL82h0h0S8YOoFL72h0h0S8YOnFM72h0h0S8YOnFN61i0h0S8YOnFN61i0h0S8XOoFO51j0g0R8YOoFO51j0g0R8YOoFO51j0g0R8YOoFO51j0g0R8YOoFO60i0h0R8YOoFN71h0h0R8YOoFN71i0g0Q8ZOoFN71k0e0o7]OnFM80m07iN5T9GgHOWN9R9HhHNVN9S9IlH7T7IlH7S7KlH5T7KmH3T7NkH2U7NkHMPN0U93kHLQN1T93kHLRNOT95jHLRNOS96kHKRNOS96kHJTNOR96kHJSN0R96kHJSN0R96kHJ[76S2O101N10000O10001O00cFOT70mH0S70mH0S70mH0S70mH0S70mH0S70Z200000000000000000`F0Y70gH0Y70gH0Y70gH0Y70fH1Z70eH1Y70gH0Z7NgH2Y7NgH2Y7NgH2Y7NgH2Y7NhH1X7OhH1X7OhH0Y70gH0Y70`41fM0000001O0000000000000O100000000O100000O010000000000000000000001O0001O00001O0000000000LMdD3`;000001N1000XOOjE1V:OjE1V:OXE0=0[:0XE0j90aG0eN0j90aG0eN0j90aG0eN0j91`G0eNOk91`G0eN0i91aG0fNOi91aG0fNOi91aG0fNOi91aG0fNOi91aG0fNOi91aG0fNOj90`G1fNNk91_G1fNNk91_G1fNNk91_G1fNNk90aG1dNOk90aG1dNOk90aG1dNOk90aG1d8O\\G1d8O\\G1d8O\\G1d8O\\G1d8O\\G1d8O\\G1U:00O10Zb20f]M1IOfD1Z;0eD0[;0dD1P;NRE001N1P;NRE001N1P;NRE001N1P;NRE001N1P;NRE001N11Oi:OXE001N11OU;0jD20NV;0jD20NV;1hD22MV;1hD21NW;6iDJX;;_OC\\E002L;h:C\\E1N2O9g:EZE101O:3D\\:0bE101O:3D\\:0bE101O;2CW:OiE2O001O;2CW:OiE2O001O;1DX:NiE2O001O<0CY:NiE2O001O<0CY:NiE2O001O<0CY:NjE1N1000<1C]:0bE10001O52I]:OdE1O0O2O52I]:OdE001O1N62I]:OdE00001N62Jh:OXE1O52Jm:1QE1`;O\\f<"}}, {"image_id": 58, "score": 0.5277044177055359, "category_id": 7, "segmentation": {"size": [500, 500], "counts": "ni]21;4L2o=KTB4Mi0_=\\O_BONi0R=SOQC;KR1P=gNPCo1n<=N2N3L4L5K3N1O2N2O0O2O000O1000001N1000000O1000000H801O1N3N1O2N1N2O001O00001N1000001O0000001O000O2O00001O1N4M3M1N2N1O2M201N1O1O1O010O10O01000O010O1O11N2O001O001O00001O00001O00O10O100000O100O010OJ61O11O11O00O00010O00000000000000O100O010O00O11O001nJfEj4Z:810O001O1000O01O00001O01O000O101N101N2N2N2N2O0O2OO2N101N2N2N2O0O2O001O000000O2O1O0O3M2N2N2N101N2N11O0O2O001O2N001O001N1001O1O1N2O1N2N3L4M101N2N10000001O00001O001O001O0O2O01N1O2O0O2O0O101N1O1mKhDj3Y;SLiDm3W;QLlDm3U;RLkDP4\\;0O1N3O0O101O0000001O0001O0O2O1O1O001N2O00001N1001O0O10001O00000O100O2O01O001O0O10001O0000000000000000000000000000O10000001O001O000O2O0000000ZLZD]3g;`L]D_3d;`L\\D`3d;`L\\D`3d;cLXD^3i;61N1000000000000O2O001O001O2M3N1O1kLjCj2W<SMlCl2T<SMmCm2S<RMoCm2R<RMnCm2S<RMnCn2S<QMmCo2\\<000001N1000000O2O1N3M3L3L6K>AcJ"}}, {"image_id": 58, "score": 0.2827652394771576, "category_id": 4, "segmentation": {"size": [500, 500], "counts": "jiQ11?003IZ1n;Z2A9G7C<N2N2O1N100O1O1O1O1O1O1O1O1O100O100000000010O00010O01O011OO01000O010OO1O1O2O000O2O001N101O00000O2O00000O100O100O1O1O2O0O1O100O1000000000O10000000000O10O100000O10O2O0O1000001N10000000001O0O11O000O1000000O2O000O101O001N101O010O010O10O010O00010O01O10O01O00001O000001O01O00000001O000001O00100O2N1ORFcJf9\\5VFiJj9V5TFlJm90TFS5k9kJXFT5i9jJXFV5h9iJZFW5f9gJ[FY5e9gJ\\FX5P:1O0O100O101N1N2L5N101O0O2O1O1O10N101O0O2O1O2M3N1O0O2O001O001OO10000O2O0O2O1N2L4J6N2N2N101N1001O0O2N2N1N5L7H2O2O001N101O000000O100O100O2I6M3O100O2N101O1N11N1O101N101O00001N103M3M3M000O10O2K4M3O1O100O100O100O10000O2OO2O00001O0000001O0O10001O0000000000000000O10000000O100000O11O00001O0O101O008H1N2O1O001N10000000000000O10000O100O1O001000000101N1O2N1O1O001oJeEg4e:dKVEm3j:QLXE2O\\3i:bLXE10]3h:aLZE1O]3h:aLYE10^3g:`L[E1O^3f:aL[E1O^3f:bLYE10^3g:aLYE10^3g:aLYE2O\\3i:bLXE2O\\3i:bLXE2N]3j:aLWE4N[3k:bLVE3O[3k:bLVEn3i:SLVEn3j:SLUEm3k:=10O1O12N2N1cKTEQ4l:lKWE8J]3o:YLYE9J]3n:XLZE9J^3Y;`LhD`3X;`LiD3Ln2\\;mLiD5Lm2[;nLjD3Lo2[;lLjD4MP3X;lLlD3LQ3X;kLmD3M5I_2];YMmD3M4K_2\\;YMlD4N2L`2Z;YMnD3M4K`2i;\\M\\D4K`2i;\\M\\D4K_2k;[M[D6J_2k;[M\\D5Ha2[<^MfCb2Z<^MfCb2[<]MeCb2\\<\\MfCd2e<0000O01O1001N4M2M2O0O2O1N8I1N2N2N101N101N10001O0000001O00001O001O1O1O001N2N3M4L6I8]Oif3"}}, {"image_id": 58, "score": 0.07151065766811371, "category_id": 11, "segmentation": {"size": [500, 500], "counts": "^Xg1l16[Nn<k2ZO>TDaLM4J;j9W3UFaL2l0d9U3ZFPMa9S3[FTM`9m2^F]Me0WNl7]4^G]Me0VNm7Z6f01O1O0O2O001O001O1O3M2N2N001O00GXGfIh8Z6YGeIg8Z6[GeIe8[6[GfId8Y6^GfIb8Z6^GfIb8Y6_GgIa8Y6_GgIa8X6`GhI`8W6aGjI^8V6bGjI^8W6aGiI_8X6`GhI`8X6_GiIa8X6^GhIb8Y6\\GhId8Y6ZGhIf8c6000O100000O10001O001O0000001O01O000001O000000000O1000000000000000O1M37I01O000000000000000000000000000001O00000000000000000O11O000001O0000000000000000000000000000000000000000O10000001O000000000000000001O000000000000000000000000000O1000000001O000001O0000000010O0000000000O0100000000000000O100001O00000000001O000000001O0000O1000000O100000000O100000O10000000001O000000000000000000000000O10O100000000000O10O110O00000000000000000000000000000000000000O1000000000000000000000000000001O0000UObG`J^8`5cG_J]8a5bG`J^8`5aGaJ_8Z60000000000000O1000000000000000000000000G`G^I`8a6bG^I^8b6cG^I\\8R6aGUJ5HZ8c5`GfJ2N5IY8c5aGeJ2N4JY8c5`GfJ2N5HZ8d5_GgJ1N6FZ8U6_GVJ7EZ8d6fG\\IZ8d6fG\\IZ8d6gG[IY8e6gG[IZ8d6gG[IY8f6fGZIZ8f6:0000000000O2O0O100O1O1fIPGc53\\Jn80PGe48dKY9DaFg4;ZK[9N\\FW4KSL`0D\\91ZFV4MSL]:FgEV4OQL[:IfEV4OPLf:P4ZEPLf:P4[EoKe:Q4[EnKf:R4ZEnKg:R4YEmKg:S4YElKh:T4XElKh:T4YEjKh:V4;0000000001O00000O1000000000lDlKh:T4XElKh:T4XElKh:T4XElKh:g3nDdL:Eh:T4XElKi:S4WEmKi:S4WEmKi:S4<01O00001N101O1O2N2N3L3M3M3B>VM^CZ2W>`MSB6c9"}}, {"image_id": 482, "score": 0.0516388863325119, "category_id": 7, "segmentation": {"size": [375, 500], "counts": "mof511010O102P3"}}, {"image_id": 482, "score": 0.0516388863325119, "category_id": 7, "segmentation": {"size": [375, 500], "counts": "\\Sg5"}}, {"image_id": 482, "score": 0.05109706521034241, "category_id": 5, "segmentation": {"size": [375, 500], "counts": "\\Sg5"}}, {"image_id": 482, "score": 0.05109706521034241, "category_id": 5, "segmentation": {"size": [375, 500], "counts": "WPg54Q3"}}, {"image_id": 482, "score": 0.050705913454294205, "category_id": 18, "segmentation": {"size": [375, 500], "counts": "\\Sg5"}}, {"image_id": 482, "score": 0.050705913454294205, "category_id": 18, "segmentation": {"size": [375, 500], "counts": "oof512020N0O0n2"}}, {"image_id": 482, "score": 0.050326284021139145, "category_id": 13, "segmentation": {"size": [375, 500], "counts": "hof5f0n2"}}, {"image_id": 482, "score": 0.050326284021139145, "category_id": 13, "segmentation": {"size": [375, 500], "counts": "\\Sg5"}}, {"image_id": 482, "score": 0.05028878524899483, "category_id": 15, "segmentation": {"size": [375, 500], "counts": "hof5e0o2"}}, {"image_id": 482, "score": 0.05028878524899483, "category_id": 15, "segmentation": {"size": [375, 500], "counts": "\\Sg5"}}, {"image_id": 1048, "score": 0.28616538643836975, "category_id": 5, "segmentation": {"size": [500, 375], "counts": "ikX17Z?7C>H8I9H2L4A>J6N3@iM_CY2`<kM[CW2d<lMYCU2g;bMfD4Jh2n:VMVE3M3Le2]:[MdE2N2OS3U:k1I6L5O1OGWFiJh9b5O01O0001O1O010O1O01O001O0O2O010O0100000000O100000O0001O0010O01000O10O01O1O100O100O10000000000000000O10000000000000000O100O1O100O1O1O1001O00001O001O0000O1O100O100O101O0001O00010O0010O01O00000010O0001O10O10O10O01O010O001O1O010O001O000010O100O002O4K4M0O01O001O2M2O2N2M22N4K3N2M6K3L4L3M2O0O001O1O2N4L2N1O1O2N2N3M4L=C1O1O001O1O2Nc0]O2N1O1fMRCl1o<QNTCn1m<PNTCP2m<lMWCS2V=O1O2N2N2N1O001N3N2ZN]Bj0J[Og>2^ALe>O_AN\\\\3OiRM0O2O1O00O2NYhT1"}}, {"image_id": 728, "score": 0.0516388863325119, "category_id": 7, "segmentation": {"size": [335, 500], "counts": "\\bS5"}}, {"image_id": 728, "score": 0.0516388863325119, "category_id": 7, "segmentation": {"size": [335, 500], "counts": "\\bS5"}}, {"image_id": 728, "score": 0.05109706521034241, "category_id": 5, "segmentation": {"size": [335, 500], "counts": "\\bS5"}}, {"image_id": 728, "score": 0.05109706521034241, "category_id": 5, "segmentation": {"size": [335, 500], "counts": "\\bS5"}}, {"image_id": 728, "score": 0.050705913454294205, "category_id": 18, "segmentation": {"size": [335, 500], "counts": "\\bS5"}}, {"image_id": 728, "score": 0.050705913454294205, "category_id": 18, "segmentation": {"size": [335, 500], "counts": "\\bS5"}}, {"image_id": 728, "score": 0.050326284021139145, "category_id": 13, "segmentation": {"size": [335, 500], "counts": "\\bS5"}}, {"image_id": 728, "score": 0.050326284021139145, "category_id": 13, "segmentation": {"size": [335, 500], "counts": "\\bS5"}}, {"image_id": 728, "score": 0.05028878524899483, "category_id": 15, "segmentation": {"size": [335, 500], "counts": "\\bS5"}}, {"image_id": 728, "score": 0.05028878524899483, "category_id": 15, "segmentation": {"size": [335, 500], "counts": "\\bS5"}}, {"image_id": 748, "score": 0.0516388863325119, "category_id": 7, "segmentation": {"size": [333, 500], "counts": "TcR5"}}, {"image_id": 748, "score": 0.0516388863325119, "category_id": 7, "segmentation": {"size": [333, 500], "counts": "TcR5"}}, {"image_id": 748, "score": 0.05109706521034241, "category_id": 5, "segmentation": {"size": [333, 500], "counts": "TcR5"}}, {"image_id": 748, "score": 0.05109706521034241, "category_id": 5, "segmentation": {"size": [333, 500], "counts": "TcR5"}}, {"image_id": 748, "score": 0.050705913454294205, "category_id": 18, "segmentation": {"size": [333, 500], "counts": "TcR5"}}, {"image_id": 748, "score": 0.050705913454294205, "category_id": 18, "segmentation": {"size": [333, 500], "counts": "TcR5"}}, {"image_id": 748, "score": 0.050326284021139145, "category_id": 13, "segmentation": {"size": [333, 500], "counts": "TcR5"}}, {"image_id": 748, "score": 0.050326284021139145, "category_id": 13, "segmentation": {"size": [333, 500], "counts": "TcR5"}}, {"image_id": 748, "score": 0.05028878524899483, "category_id": 15, "segmentation": {"size": [333, 500], "counts": "TcR5"}}, {"image_id": 748, "score": 0.05028878524899483, "category_id": 15, "segmentation": {"size": [333, 500], "counts": "TcR5"}}, {"image_id": 947, "score": 0.22138044238090515, "category_id": 5, "segmentation": {"size": [500, 361], "counts": "]mS12b>OdA3Mb02[Om=0RBW1MmN5Lc=3YBZ14cNk=4PBi05SOQm1l0YaN>I1OL5M20M:A:I8^BQNZ=m18N2ON3M4GQNgBV2T=53H7M1OO3L4N6LL5K4N10N3M4N1ON4L3N02M3O2NO1O2N10O2N2O3MM201O1001O1N10N1O2O10O10O1O1N2N2000O1O12L3K5N2O1N1N2O2J5I7O2M2N2PObAc01\\Od>c07HVAEl>3RAN[lR3"}}, {"image_id": 947, "score": 0.06301834434270859, "category_id": 18, "segmentation": {"size": [500, 361], "counts": "Sei0616g>G]An0m=POUB5Jn0f=nN`B2MX1Z=eNiB4La1Z=^NfBm1P=PNTCX2l<hMTCY2S=01kMgBm1Y=RNhBo1W=PNkBo1U=RNiBo1V=9GfMUC[2k<gMRC[2l<70`MSCY2n<dMTC[2m<cMUC]2R=O00IdMUC]2j<7O1O1O11O0O2O0O10O101I^MYCc2f<7N01O1O100O10O101O0O2OO1O100O0100O1O2M2O1000O10000O10O1O2N1O11N1JbCVM_<i2dCTM\\<k270O100O0N3O0O101O010O10O100O100O1N101O1O100O100O2N0O2M2O2M3M3O1N3M2O2OO1O1O100O11N1N2J7F]B_Ng=^1\\B_Nf=`1700O100O2M2jNiAm0Y>ROiAi0[>VOgAf0]>XOdA5K8n>BYA1lci2"}}, {"image_id": 1315, "score": 0.0516388863325119, "category_id": 7, "segmentation": {"size": [378, 500], "counts": "Xbh5"}}, {"image_id": 1315, "score": 0.05109706521034241, "category_id": 5, "segmentation": {"size": [378, 500], "counts": "Xbh5"}}, {"image_id": 1315, "score": 0.050705913454294205, "category_id": 18, "segmentation": {"size": [378, 500], "counts": "Xbh5"}}, {"image_id": 1315, "score": 0.050326284021139145, "category_id": 13, "segmentation": {"size": [378, 500], "counts": "Xbh5"}}, {"image_id": 1315, "score": 0.05028878524899483, "category_id": 15, "segmentation": {"size": [378, 500], "counts": "Xbh5"}}, {"image_id": 152, "score": 0.08725378662347794, "category_id": 4, "segmentation": {"size": [367, 480], "counts": "d_j0?X:k0J5L20000O100O100O1N3[Oe0D;H9L4N3L3M4L4K5H7J5N20000O100O1L4L4L4K5L4M300N2O1^K[KVN2d3c4UNPLf1Q4YNRLd1o3[NTLb1m3^NUL_1l3bNTL\\1m3dNTLY1n3gNSLW1n3iNSLT1o3lNRLQ1P4nNSLo0n3QOSLn0m3ROTLl0m3SOVLk0j3UOYLh0g3XO_La0b3_O[Lc0f3]OXLc0j3]OULc0l3]OSLb0o3^OQL`0Q4@oK?R4ASL;l3EXL9f3G\\L8c3H^L8a3H`L8_3GbL;\\3EdL;\\3EdL:]3FcL9^3GbL8_3HaL7`3I`L7`3I`L7`3IaL6_3JaL8]3HcL9\\3GdL:[3FfL;X3EhL:Y3FgL9Z3GgL7Z3IfL7Z3IfL6[3JfL5Z3KfL5Z3KfL6Y3JgL8W3HiL:U3FkL<S3DmL?P3AoLc0n2]OSMa0n2_OSM>o2BQM<Q3DQM9P3GTM3n2MSM2m2NSM4k2LUM7h2IWM=d2C[Md0_2\\O`Mj0[2VOeMl0Y2TOiMi0X2WOjMf0W2ZOlMb0U2^OnM=T2CnMO^21eMI^27hL[NdN`1c45iL^N^NQ2X4BXM`N\\NU2W4[O\\MbNZNh2g3fNoMdNWNo2b3]NVNfNUNT3_3WN\\NgNRNT3`3VN]NhNRNR3b3VN[N\\2f1cMZN\\2g1dMXN[2j1eMUNb1VN]Mf3R1SN]2j1dMUNb2e1_MYNf2c1[M\\Ng2a1^MdMWNC]4d2aMbMZNGV4c2eMaMYNKS4b2eMdMXNHT4f2bMcM[NDT4l2^M`M_NBT4P3[M^M_3c2`L^M`3a2`L_M`3a2f21000O0M3N2O1021O0O2O3M05H5K3L5K4N2M2000000000001O4Jb0aNZF1gUh2"}}, {"image_id": 1042, "score": 0.605176568031311, "category_id": 3, "segmentation": {"size": [375, 500], "counts": "g^Q4351OOi:OXE2N2N0R;OnD9Q;7F^O\\Ee0e:8HUOaEm0V:oNmE4Mn0T:QOlEW1P::H_NYFb1a9[N`F5M[1h9<1N2N2L4^OQFQOY:h0fEYOb:o0O003MM3O1I_EWOb:i0^EWOb:P1O00000000J]EWOd:n001O0oFPO[7Q1cHRO[7n0VHFe7:YHIf77^GmNb0Q1P89gGgNFR1c8n1O0000O10000O1N3N1O2N2N2O2M4M2TNkF@0Y1_9eNXGT1h9M2O3M3M1O1O1O1O001O010O0000001000O0001O00001O1O001N10001N1O2O2M4KfPe0"}}, {"image_id": 1042, "score": 0.23893219232559204, "category_id": 15, "segmentation": {"size": [375, 500], "counts": "[VZ478ONLb:f0ZE_Od:k0_EPOX:R1eEPO[:V1O110O1O2[GeNj6\\1oHjNQ7W1eHSOZ7n0\\H`NZOf0Y8l0YH@c7e0THBj7V2O01N2M3N2L4N2O4K3M3L3N3N2]NjFa0Y9ROhFD3X1X9dNjF0;Z1l9M4L2M2O2N1O1O1O101M2O1O001O01OO2O00001O001O0000000000010N2N3M2N200O2M4Jndd0"}}, {"image_id": 698, "score": 0.6925498247146606, "category_id": 7, "segmentation": {"size": [375, 500], "counts": "\\l4X1o9kN[Fa1[9eN]Fa1_9`0K8H3M3BYMgGi2V8]MeGf24TMh7f3L5J5dHRLi6T4SIoKj6T4SIoKk6_4O1O1OEUIlKj6U4WIiKi6X4WIhKi6X4YIfKf6Z4\\IdKd6]4_I_KY6j4:O03N:E2O1O1N2O0RJdJa5]5[JiJb5X5[JkJc5W5[JkJd5T5^JjJc5U5_JiJb5V5aJfJa5Y5?O0O2N2O1N2O02O2N2M3M3M2M2YJ]JZ5d5dJ^JZ5c5eJ_JZ5b5dJ_J[5a5fJ_JY5b5hJ\\JX5e5jJYJT5h5=00N3M2N3O001101N2N4L2N1O0bJUJQ5k5mJWJR5i5mJXJS5h5mJXJR5i5nJWJR5i5nJWJQ5j5oJVJQ5k5oJSJR5m5oJQJQ5P6;1O2N1O1N3N4L2N1N2O0O1O101O0001O001O000100O2N1OO10O01O0010O1O10000000001O010O2O0O1O100N1000O01O0100O010O1O12N2N100O10O010O0010N10O01O100O1000000O11O010O010O1O0010O00000O1O1O1O1O10000O01010O01O1O2N100O001O00O100O1O1O1O1O1O10O110O1O1O2N1O1O001O00001O00001O1O1O1O1O001N101O001O1O1O2N1O1O000000001N10000O10001N2O1O1N2O2N3M4L1N2OO100O1N2O100O1O100001N2N3aLVJQN1X2W6WOcJb0a5kN_Kd0f4iNnKYOlM>J7l6_OkL9^7KUab2"}}, {"image_id": 698, "score": 0.22787827253341675, "category_id": 4, "segmentation": {"size": [375, 500], "counts": "T?h13YO<SO[7n3F8J?A4M30O001O00001O000001O0001O0000000000000000000000001O0000000010O000000000001O000O101O00001O000000O10000O10000O10000O10000O10000O100O100M3N2O1O1M3N2O1O1^OdJiJ\\5V5fJhJ[5W5gJgJ[5W5gJhJY5X5hJfJY5Y5hJgJX5Y5iJeJX5[5hJeJX5[5hJeJX5[5hJeJX5[5iJcJX5]5hJcJX5]5hJcJX5]5hJcJX5]5iJbJW5^5iJaJX5_5hJaJX5_5iJ`JW5`5iJ_JX5a5iJ^JW5a5`000O1AlI[KT6d4oIYKR6f4PJXKQ6h4QJVKo5i4TJTKm5l4TJRKm5m4?001dIRKm5n4RJTKm5l4RJUKn5k4QJWKn5j4PJWKP6i4oIYKP6h4mIZKS6f4lI[KT6f4jI\\KU6S5000AkI\\KU6c4mI[KT6e4nIYKR6f4QJWKP6h4SJUKn5k4TJRKm5m4?00O100000000001O001dIRKm5n4QJUKn5l4oIWKP6j4mIXKS6h4kI[KT6f4jI[KV6T5OO1AmIZKS6e4PJXKQ6h4RJTKo5k4?O100O10000O100001O0000001O00001O001cISKn5l4TJRKm5n4>00O100O10000O100000000000000000000001O000000O10000O100O100O100O2O0001N101O001O001O00001O00O100O100O1O1O1O1O100O2O01N2O1O1O1O1O1O0eIUKj5l4TJVKk5j4SJYKl5h4SJYKl5f4VJXKk5h4UJWKl5i4VJUKj5j4b000O100O1O1O1O1001O2N1O001O1cIVKk5j4TJXKk5i4SJYK6JT5m4eJ[K5JU5k4eJ]K4JV5j4eJ\\K4LV5h4fJ\\K4KW5i4eJ[K6KU5j4eJ[K7IU5l4eJYK8IT5o4cJWKP6i4RJTKo5l4>1O1O001O1O00O100OYLPKfM0^2P5KSKcM2_2k4MUKaM5MMP2i4kMWK=KV17bN4I3S2_4oMZK:NU14cNn0i1f3UN[K80d0H]O;FT1e1^3\\N\\K62a0J_O8GU1e1[3^N]K4?4_OLn1]1g2^N^K5`01_ONl1^1g2^N]K62KL44Ll1`1f2^N[K92JM16Lk1b1e2]N[K<0JONf2^1]2kNmJK0Kf2^1[2POlJI4Gg2_1U2WOlJE9Df2`1T2K[N4d1M\\N3d1M]N2c1N]N2c1N^NlN^Lh0V5:jNEW19kNFV18lNGU18mNFU17mNHV1G`JJ]4<W1EbJK[4<U1DeJM]49P1FgJO[49o0EH9m5M3N2NU[U2"}}, {"image_id": 698, "score": 0.14690187573432922, "category_id": 20, "segmentation": {"size": [375, 500], "counts": "SV<27R2Q9?mF`M]8OdGk2[8YMaGi2]89FiLSHX3m7jLQHV3n7lLPHU3o7910O1O1O0I8O2N100O100IQLfHP4X7TLeHl3[7TLdHm3\\77O1000000000000O100000000O1000000HeKTIZ4m6fKRI[4n6fKQIZ4o671N100O100O10O101N1O101O001O0O1000000O100O1O1000000001O0000001O00O10000O1O00100O0100010O01O001O0010O0O00100O1O010O1000000010O0010O0001O00O100O100O01000O11O00010O0001O01O00O1000000O100O01000010O00001O0001O0000000O100O100O0100010O01O001O00000000000000O100O10000001O1O1O1O1O1O001O000000000000000O100010O01O001O001O002N1N2O001O001O0O2O1O1O1O3M6J1O001N10001N100O2ZLUH^3k7aLWHS3NRMk7JYHR3NRMk7JXHS3ORMR8l2oGSMR8d2YHZMg7c2]H[Me75hGm1X9QNkFk1Y9SNiF5JS1S:jNQFP1T:mNoE6I?g:^O]E4L0i:K]E2N0g:L\\E3OOQ;OQEOc^d2"}}, {"image_id": 1175, "score": 0.6248685717582703, "category_id": 11, "segmentation": {"size": [375, 500], "counts": "_<n2f8=E;E3M2O2M2O2M2^HPL[7V400OL5O1000O10000000000000000000000000000O10000000001O000000001O000O100001N10000O100000000000000O100000000000000000000000001O0O100000000000000000000000000000O100000000000000000000000000000O10000000000000000000O100000000000000000000000000000000000000O10000000000000001O00000000000000000000000O1000000000O100000O100O1N2O100001O1O001O0000000001O000001O00000000O100000O10O10000O100O100000O010000000000001O000001O01O0000001O00000000000000O1000O10O1000O10O10N200O1O100O11O001O001O1O001O010O000000001O01O000000O10O100000000O010O1O1O1O1O1O1O1001O001O2N2N100O00001O00000001O0001O0000000000000O010000000000000000000000O1000001N100000001N100000000F`H]L`7b3aH]L`7c3`H]L`7c3`H]L`7c3aH\\L_7d3aH[L`7e3`H[L`7e3`HZLa7f3`HYL`7g38001O00000000000000JVH`Li7`3YH^Lg7b3ZH\\Lg7d360001O000O10000N2N3N1O1GgGTMY8k2hGUMX8k2iGSMX8l2iGTMW8l2jGSMV8m2jGSMV8m2iGTMW8l2iGTMW8m2hGTMW8l2iGTMW8l2hGUMX8k2hGVMW8V3O1O001O001O0O10000001O00100O01O1O1O010OGoGlLQ8T3oGlLQ8T3PHkLP8j2oGXM2No7j2oGXM2NP8i2nGYM2NP8i2nGYM2Oo7g2PHZM1Oo7g2PHZM1Oo7g2PHZM1NP8h2oGZM1NP8i2nGYM2NP8i2nGYM2NP8i2nGYM2NP8i2nGYM2NP8i2nGYM2MQ8j2mGYM3LP8k2mGYM3LP8k2mGYM3LP8l2lGXM4KQ8m2kGXM5JP8n2kGXM]8R3O00001O1O002N3M1O1O1O1O7I100O1O001\\HSL\\7m3cHTL]7m3`HUL`7Q4010OO10O1000000J`HUL`7k3aHTL_7k3cHTL]7l3dHRL]7n3600O100O1O1N2O11O2N1O1\\HTL[7m3bHUL_7j3`HWL`7P401O00001O0000010O000000000000O10000O1H`HYL`7g3aHWL`70_Hc32\\L_7OaHd3g7[L[Hd3e7\\L[Hc3f7]LZHc3f7]L[Ha3f7_LZHa3f7_LZH`3o701ROkGfM03Y8V2jGcM03Z8m1gGoM3MO5Y8k1_HRNd7b1`G_Ni9\\1?BfETOb:LcE21N]9"}}, {"image_id": 1175, "score": 0.562627911567688, "category_id": 7, "segmentation": {"size": [375, 500], "counts": "]hU142`0d:k0B4K2O5EWN]Fl1a9UN^Fl1a9UN^Fl1a97N1O1N101O00001O0hFfMS9Z2lFhMR9Z2mFfMS9Z2lFgMT9Y2lFgMT9Y2lFgMT9Y2lFgMT9Y2lFgMT9Y2lFgMT9Y2lFgMT9^200000000000001O0000000000001N10000000000000O1000000000000O100O01O2O0O101O000000000000000O10000000000O10000000000000000000000000000000000000000000000000000O1000000000O10000000000000000000000000000000000000000O010O1N2O10000001O1O2N001O000000000000000000000000O1000O0100ISGcMn8]2SGbMm8^2RGdMm8c201O1O00001O00000000000000000000000000000000O100GUGeMl8d2O00000001O01O00000000000000000000O100000000000000KTG_Ml8a2TG_Mm8`2TG_Ml8a2TG^Mm8a2TG_Ml8a2UG^Mk8b2UG^Mk8b2UG^Mk8b2UG^Ml8a2TG_Ml8a2TG_Ml8a2TG_Ml8a2TG_Ml8a2TG_Ml8a2500O1000000O10O01O100O1KhFkMX9Z210O001O10O01O01O000JiFlMW9T2iFmMW9R2iFnMW9R2iFmMX9S2iFlMW9T2iFlMW9m1hFUN1NW9m1hFTN3NU9n1iFRN3OU9n1=O1N2O2O0O1000000O100OVFYNf9g1YFZNg9f1XF[Nh9e1XF\\Ng9d1YF\\N;Mn8g1gF\\N;Mn8g1gF\\N;Mn8g1gF\\N;Mn8g1gF\\N;Mn8g1gF\\N;Mn8f1iF\\N9Nn8f1iF[Nf9e1[FZNe9e18JoEdNQ:[16O1O1N2N3N1O1001O000000000000000000000001O0O1O100O1N2N200UOZEd0g:\\OYEd0h:ZOZEd0g:\\OYEd0g:]OXEc0h:]OWEd0i:\\OWEd0i:\\OWEd0i:]OVEc0j:5O100000000001O000O1WOWEd0n:N3N2N1J7GhVe0"}}, {"image_id": 1425, "score": 0.0516388863325119, "category_id": 7, "segmentation": {"size": [225, 400], "counts": "`lg2"}}, {"image_id": 1425, "score": 0.0516388863325119, "category_id": 7, "segmentation": {"size": [225, 400], "counts": "`lg2"}}, {"image_id": 1425, "score": 0.0516388863325119, "category_id": 7, "segmentation": {"size": [225, 400], "counts": "`lg2"}}, {"image_id": 1425, "score": 0.05109706521034241, "category_id": 5, "segmentation": {"size": [225, 400], "counts": "`lg2"}}, {"image_id": 1425, "score": 0.05109706521034241, "category_id": 5, "segmentation": {"size": [225, 400], "counts": "`lg2"}}, {"image_id": 1425, "score": 0.05109706521034241, "category_id": 5, "segmentation": {"size": [225, 400], "counts": "`lg2"}}, {"image_id": 1425, "score": 0.050705913454294205, "category_id": 18, "segmentation": {"size": [225, 400], "counts": "`lg2"}}, {"image_id": 1425, "score": 0.050705913454294205, "category_id": 18, "segmentation": {"size": [225, 400], "counts": "`lg2"}}, {"image_id": 1425, "score": 0.050705913454294205, "category_id": 18, "segmentation": {"size": [225, 400], "counts": "`lg2"}}, {"image_id": 1425, "score": 0.050326284021139145, "category_id": 13, "segmentation": {"size": [225, 400], "counts": "`lg2"}}, {"image_id": 1425, "score": 0.050326284021139145, "category_id": 13, "segmentation": {"size": [225, 400], "counts": "`lg2"}}, {"image_id": 1425, "score": 0.050326284021139145, "category_id": 13, "segmentation": {"size": [225, 400], "counts": "`lg2"}}, {"image_id": 1425, "score": 0.05028878524899483, "category_id": 15, "segmentation": {"size": [225, 400], "counts": "`lg2"}}, {"image_id": 1425, "score": 0.05028878524899483, "category_id": 15, "segmentation": {"size": [225, 400], "counts": "`lg2"}}, {"image_id": 1425, "score": 0.05028878524899483, "category_id": 15, "segmentation": {"size": [225, 400], "counts": "`lg2"}}, {"image_id": 1378, "score": 0.08214609324932098, "category_id": 11, "segmentation": {"size": [375, 500], "counts": "fP1290a:b0[EBY:j0dEYOX:W1C=K4G8N2O00001O00000000000O2O00000000000O100N2000000O100000000000000O1000000000O11O0000000O100000000O100O100O100O10000O100O100O1O100O101N10000O10000O10000N2N2O1O1O1O1O1O1O1O1O100O1000O010001O0O10000O100O1000000O1000000000000O100000000O1000000O1O010O1O100O100O100O1000001N1000000000000O100000000000000O10000O10000O100O1000000O10000000000O100000000O10000O1000000O100000000O1000000000000000O1000O1000000000000O10000O1O1O1O100O100O100000000O1000000000O1000000N2N2O1000000O10000000000000O100000000000000000000000000000000000000iHfKQ7Z4oHfKQ7Z4oHfKQ7Z4oHfKQ7Z4nHhKQ7X4oHhKQ7X4oHhKQ7X4oHhKQ7X4oHhKQ7X4oHhKQ7X4oHhKQ7X4oHhKQ7X4oHhKQ7X4oHhKQ7X4PIfKQ7Z4oHfKQ7Z460000000000000000000O101O00O100000000O10001O000000000000000000000O10000000000000000GdHWL\\7i3dHWL\\7h3fHWLZ7i3fHWLZ7`3cHaL4OY7`3dH`L3OZ7`3eH_L30X7a3eH_L30X7a3eH_L30X7a3eH_L30X7a3eH_L30X7a3eH_L30X7b3dH^L40X7b3dH^L40X7b3dH^L40X7b3dH^L5OW7c3dH^L5OW7c3dH^L5NX7d3cH^L5NX7d3cH^L5NX7d3cH^L5NX7d3cH^L6MW7e3bH_L7LW7e3bH^L8MV7e3bH^L8MV7e3bH^L8MV7e3cH^L6MW7e3cH^L6MW7e3cH^L6MX7c3cH`L5MX7c3cH`L5MX7c3dH_Lf7W3WHnL3Kg7V3VHoL3Kg7V3WHmL3Mg7T3WHoL2Mg7T3XHnL1Nh7j2SH[M4M1Nh7j2SH[M4M1Nh7i2UHZM3O0Nh7_2THfM1N4M00h7]2THgM2N2N00h7i1RHgN3C1O2N00h7]2UHfM1O2N00h7]2UHfM1N3N10f7^2UHfM1N4M00g7_2THfM2M3NQ8_2jGeM3N]8]2`GeM3M^8^2_GeM4L]8_2`GcMj8]2800LjFiMT9W2oFgMP9X2QGhMo8X2QGhMo8W2RGiMn8W2RGiMm8X2SGhM3Na8Y2\\GiM3Nb8W2]GiMo8V2QGjMP9m1jFWNa9g1cFUN_9f1;N3N1N3J5M3M<QOWE7\\;EWg;OooC0]60YG0o10h61XGOo12h6OXG0\\1OeN1O1g80YG0[1NfN1O1g80YG0[1NfN1O1g80XG1g0ME1F0O1^8NbG2O11M200092D011f8OYG1<MG091E101f8OYG1\\1MfN1O2g8NYG1[1NfN1O1h8OXG1[1NfN1O1h8NYG2d1O[N1R9OnH1R7OnH1S7NmH2S7NnH0]90\\^10daN1O0dDO00g:2YEN01f:1ZENO2g:0ZENO2g:0ZENO2g:0ZENO2g:0YEO01g:0YE0O0h:1XEO00h:1XEO00h:1XEOO1`:MaE40NO1`:MaE40NO1_:NbE30NO1_:NbE30NO1`9McF0;1C4ONN1a9MdF00O02L40NO0R8LXI2iN02N03K31NO0R8NVI0kN11N03J33NNOR80VINlN10O0>LFOOT8MVI0kN11M13J42L01Q8MWI0lN0b04\\OLO3P8LYI0jN1c03DO_:ObE1R;01O00000000001O000000000O10Zd2"}}, {"image_id": 1243, "score": 0.7841067910194397, "category_id": 4, "segmentation": {"size": [375, 500], "counts": "iSZ21d;2O2N1N201N2O5EBSE?l:CRE>l:CSE?l:ATE`0j:AVEc07]OQ:m0jEVOU:X1mE`Nk9h1N1O1O00000000000O1KUN^Fk1a9WN^Fi1b9XN]Fi1b9600O10000000000000000001O0O100O101N1000O100O1000000O100000000000000001OO10000O10001O000K53M001O000000000000O101N100O1O1O2O0000O10O100000O100000O101N100O100O11O000O2N101N100O10O100O1000O0100000O1O1O2O0O1O2N1O10O2O000O10001O000000O100O1O2O0O100001O0O2O1O001O000000O2O0O2N101N1O1001O010O0101N1O00001N101N2lNSF;Q:YO\\Fc0g9XO\\Ff0\\:N10100O001O1O001O001N101N1O2N100O2O000NRPS1"}}, {"image_id": 629, "score": 0.0516388863325119, "category_id": 7, "segmentation": {"size": [500, 333], "counts": "TcR5"}}, {"image_id": 629, "score": 0.05109706521034241, "category_id": 5, "segmentation": {"size": [500, 333], "counts": "TcR5"}}, {"image_id": 629, "score": 0.050705913454294205, "category_id": 18, "segmentation": {"size": [500, 333], "counts": "TcR5"}}, {"image_id": 629, "score": 0.050326284021139145, "category_id": 13, "segmentation": {"size": [500, 333], "counts": "TcR5"}}, {"image_id": 629, "score": 0.05028878524899483, "category_id": 15, "segmentation": {"size": [500, 333], "counts": "TcR5"}}]